[
  {
    "id": "saussure-gram-031",
    "serverId": "saussure",
    "questionType": "QUIZ",
    "category": "문법",
    "stem": "물어보는 문장 끝에 쓰는 부호는?",
    "passage": null,
    "choices": [
      { "id": "1", "text": "?" },
      { "id": "2", "text": "." },
      { "id": "3", "text": "!" },
      { "id": "4", "text": "," }
    ],
    "answerId": "1",
    "timeLimitSec": 15
  },
  {
    "id": "saussure-gram-032",
    "serverId": "saussure",
    "questionType": "QUIZ",
    "category": "문법",
    "stem": "띄어쓰기가 바른 것은?",
    "passage": null,
    "choices": [
      { "id": "1", "text": "나는학교에간다" },
      { "id": "2", "text": "나는 학교에 간다" },
      { "id": "3", "text": "나는학교 에간다" },
      { "id": "4", "text": "나 는학교에 간다" }
    ],
    "answerId": "2",
    "timeLimitSec": 15
  },
  {
    "id": "saussure-gram-033",
    "serverId": "saussure",
    "questionType": "QUIZ",
    "category": "문법",
    "stem": "알려 주는 문장 끝에 쓰는 부호는?",
    "passage": null,
    "choices": [
      { "id": "1", "text": "!" },
      { "id": "2", "text": "?" },
      { "id": "3", "text": "." },
      { "id": "4", "text": "," }
    ],
    "answerId": "3",
    "timeLimitSec": 15
  },
  {
    "id": "saussure-gram-034",
    "serverId": "saussure",
    "questionType": "QUIZ",
    "category": "문법",
    "stem": "놀라거나 기쁠 때 쓰는 문장 부호는?",
    "passage": null,
    "choices": [
      { "id": "1", "text": "?" },
      { "id": "2", "text": "." },
      { "id": "3", "text": "," },
      { "id": "4", "text": "!" }
    ],
    "answerId": "4",
    "timeLimitSec": 15
  },
  {
    "id": "saussure-gram-035",
    "serverId": "saussure",
    "questionType": "QUIZ",
    "category": "문법",
    "stem": "띄어쓰기가 바른 것은?",
    "passage": null,
    "choices": [
      { "id": "1", "text": "고양이가 운다" },
      { "id": "2", "text": "고양이 가운다" },
      { "id": "3", "text": "고양 이가운다" },
      { "id": "4", "text": "고양이가운다" }
    ],
    "answerId": "1",
    "timeLimitSec": 15
  },
  {
    "id": "saussure-gram-036",
    "serverId": "saussure",
    "questionType": "QUIZ",
    "category": "문법",
    "stem": "'오늘은 날씨가 좋다'는 어떤 문장인가?",
    "passage": null,
    "choices": [
      { "id": "1", "text": "묻는 문장" },
      { "id": "2", "text": "알려 주는 문장" },
      { "id": "3", "text": "시키는 문장" },
      { "id": "4", "text": "놀라는 문장" }
    ],
    "answerId": "2",
    "timeLimitSec": 15
  },
  {
    "id": "saussure-gram-037",
    "serverId": "saussure",
    "questionType": "QUIZ",
    "category": "문법",
    "stem": "바르게 쓴 문장은?",
    "passage": null,
    "choices": [
      { "id": "1", "text": "엄마가 밥을 해요" },
      { "id": "2", "text": "엄마가밥을 해요" },
      { "id": "3", "text": "엄마 가밥을해요" },
      { "id": "4", "text": "엄마가밥을해요" }
    ],
    "answerId": "1",
    "timeLimitSec": 15
  },
  {
    "id": "saussure-gram-038",
    "serverId": "saussure",
    "questionType": "QUIZ",
    "category": "문법",
    "stem": "'너는 어디에 가니'는 어떤 문장인가?",
    "passage": null,
    "choices": [
      { "id": "1", "text": "묻는 문장" },
      { "id": "2", "text": "알려 주는 문장" },
      { "id": "3", "text": "시키는 문장" },
      { "id": "4", "text": "놀라는 문장" }
    ],
    "answerId": "1",
    "timeLimitSec": 15
  },
  {
    "id": "saussure-gram-039",
    "serverId": "saussure",
    "questionType": "QUIZ",
    "category": "문법",
    "stem": "띄어쓰기가 바른 것은?",
    "passage": null,
    "choices": [
      { "id": "1", "text": "나는사과를먹었다" },
      { "id": "2", "text": "나 는사과 를먹었다" },
      { "id": "3", "text": "나는 사과를 먹었다" },
      { "id": "4", "text": "나는사과 를먹었다" }
    ],
    "answerId": "3",
    "timeLimitSec": 15
  },
  {
    "id": "saussure-gram-040",
    "serverId": "saussure",
    "questionType": "QUIZ",
    "category": "문법",
    "stem": "'와, 눈이 온다'에 알맞은 부호는?",
    "passage": null,
    "choices": [
      { "id": "1", "text": "와. 눈이 온다." },
      { "id": "2", "text": "와? 눈이 온다?" },
      { "id": "3", "text": "와! 눈이 온다!" },
      { "id": "4", "text": "와, 눈이 온다," }
    ],
    "answerId": "3",
    "timeLimitSec": 15
  },
  {
    "id": "saussure-gram-041",
    "serverId": "saussure",
    "questionType": "QUIZ",
    "category": "문법",
    "stem": "바르게 쓴 문장은?",
    "passage": null,
    "choices": [
      { "id": "1", "text": "아빠는회사에간다" },
      { "id": "2", "text": "아빠 는회사에간다" },
      { "id": "3", "text": "아빠는 회사에 간다" },
      { "id": "4", "text": "아빠는회사 에간다" }
    ],
    "answerId": "3",
    "timeLimitSec": 15
  },
  {
    "id": "saussure-gram-042",
    "serverId": "saussure",
    "questionType": "QUIZ",
    "category": "문법",
    "stem": "'숙제를 다 했니'에 알맞은 부호는?",
    "passage": null,
    "choices": [
      { "id": "1", "text": "숙제를 다 했니." },
      { "id": "2", "text": "숙제를 다 했니!" },
      { "id": "3", "text": "숙제를 다 했니," },
      { "id": "4", "text": "숙제를 다 했니?" }
    ],
    "answerId": "4",
    "timeLimitSec": 15
  },
  {
    "id": "saussure-gram-043",
    "serverId": "saussure",
    "questionType": "QUIZ",
    "category": "문법",
    "stem": "띄어쓰기가 바른 것은?",
    "passage": null,
    "choices": [
      { "id": "1", "text": "동생이 운다" },
      { "id": "2", "text": "동생 이운다" },
      { "id": "3", "text": "동생이운다" },
      { "id": "4", "text": "동 생이운다" }
    ],
    "answerId": "1",
    "timeLimitSec": 15
  },
  {
    "id": "saussure-gram-044",
    "serverId": "saussure",
    "questionType": "QUIZ",
    "category": "문법",
    "stem": "'이름이 무엇입니까'는 어떤 문장인가?",
    "passage": null,
    "choices": [
      { "id": "1", "text": "알려 주는 문장" },
      { "id": "2", "text": "묻는 문장" },
      { "id": "3", "text": "시키는 문장" },
      { "id": "4", "text": "놀라는 문장" }
    ],
    "answerId": "2",
    "timeLimitSec": 15
  },
  {
    "id": "saussure-gram-045",
    "serverId": "saussure",
    "questionType": "QUIZ",
    "category": "문법",
    "stem": "바르게 쓴 문장은?",
    "passage": null,
    "choices": [
      { "id": "1", "text": "강아지 가짖는다" },
      { "id": "2", "text": "강아지가 짖는다" },
      { "id": "3", "text": "강아지가짖는다" },
      { "id": "4", "text": "강 아지가짖는다" }
    ],
    "answerId": "2",
    "timeLimitSec": 15
  },
  {
    "id": "saussure-gram-046",
    "serverId": "saussure",
    "questionType": "QUIZ",
    "category": "문법",
    "stem": "'내 동생은 다섯 살이다'에 알맞은 부호는?",
    "passage": null,
    "choices": [
      { "id": "1", "text": "내 동생은 다섯 살이다!" },
      { "id": "2", "text": "내 동생은 다섯 살이다?" },
      { "id": "3", "text": "내 동생은 다섯 살이다." },
      { "id": "4", "text": "내 동생은 다섯 살이다," }
    ],
    "answerId": "3",
    "timeLimitSec": 15
  },
  {
    "id": "saussure-gram-047",
    "serverId": "saussure",
    "questionType": "QUIZ",
    "category": "문법",
    "stem": "띄어쓰기가 바른 것은?",
    "passage": null,
    "choices": [
      { "id": "1", "text": "친구와놀았다" },
      { "id": "2", "text": "친구 와놀았다" },
      { "id": "3", "text": "친구와 놀았다" },
      { "id": "4", "text": "친 구와놀았다" }
    ],
    "answerId": "3",
    "timeLimitSec": 15
  },
  {
    "id": "saussure-gram-048",
    "serverId": "saussure",
    "questionType": "QUIZ",
    "category": "문법",
    "stem": "'빨리 오세요'는 어떤 문장인가?",
    "passage": null,
    "choices": [
      { "id": "1", "text": "묻는 문장" },
      { "id": "2", "text": "놀라는 문장" },
      { "id": "3", "text": "알려 주는 문장" },
      { "id": "4", "text": "시키는 문장" }
    ],
    "answerId": "4",
    "timeLimitSec": 15
  },
  {
    "id": "saussure-gram-049",
    "serverId": "saussure",
    "questionType": "QUIZ",
    "category": "문법",
    "stem": "바르게 쓴 문장은?",
    "passage": null,
    "choices": [
      { "id": "1", "text": "선생님께서오셨다" },
      { "id": "2", "text": "선생님께서 오셨다" },
      { "id": "3", "text": "선생 님께서오셨다" },
      { "id": "4", "text": "선생님 께서오셨다" }
    ],
    "answerId": "2",
    "timeLimitSec": 15
  },
  {
    "id": "saussure-gram-050",
    "serverId": "saussure",
    "questionType": "QUIZ",
    "category": "문법",
    "stem": "'정말 맛있다'에 알맞은 부호는?",
    "passage": null,
    "choices": [
      { "id": "1", "text": "정말 맛있다?" },
      { "id": "2", "text": "정말 맛있다." },
      { "id": "3", "text": "정말 맛있다!" },
      { "id": "4", "text": "정말 맛있다," }
    ],
    "answerId": "3",
    "timeLimitSec": 15
  },
  {
    "id": "saussure-gram-051",
    "serverId": "saussure",
    "questionType": "QUIZ",
    "category": "문법",
    "stem": "띄어쓰기가 바른 것은?",
    "passage": null,
    "choices": [
      { "id": "1", "text": "책을읽는다" },
      { "id": "2", "text": "책 을읽는다" },
      { "id": "3", "text": "책을 읽는다" },
      { "id": "4", "text": "책을읽 는다" }
    ],
    "answerId": "3",
    "timeLimitSec": 15
  },
  {
    "id": "saussure-gram-052",
    "serverId": "saussure",
    "questionType": "QUIZ",
    "category": "문법",
    "stem": "'공부를 열심히 하세요'는 어떤 문장인가?",
    "passage": null,
    "choices": [
      { "id": "1", "text": "묻는 문장" },
      { "id": "2", "text": "시키는 문장" },
      { "id": "3", "text": "놀라는 문장" },
      { "id": "4", "text": "알려 주는 문장" }
    ],
    "answerId": "2",
    "timeLimitSec": 15
  },
  {
    "id": "saussure-gram-053",
    "serverId": "saussure",
    "questionType": "QUIZ",
    "category": "문법",
    "stem": "바르게 쓴 문장은?",
    "passage": null,
    "choices": [
      { "id": "1", "text": "언니가 웃는다" },
      { "id": "2", "text": "언니 가웃는다" },
      { "id": "3", "text": "언니가웃는다" },
      { "id": "4", "text": "언 니가웃는다" }
    ],
    "answerId": "1",
    "timeLimitSec": 15
  },
  {
    "id": "saussure-gram-054",
    "serverId": "saussure",
    "questionType": "QUIZ",
    "category": "문법",
    "stem": "'비가 온다'에 알맞은 부호는?",
    "passage": null,
    "choices": [
      { "id": "1", "text": "비가 온다?" },
      { "id": "2", "text": "비가 온다!" },
      { "id": "3", "text": "비가 온다," },
      { "id": "4", "text": "비가 온다." }
    ],
    "answerId": "4",
    "timeLimitSec": 15
  },
  {
    "id": "saussure-gram-055",
    "serverId": "saussure",
    "questionType": "QUIZ",
    "category": "문법",
    "stem": "띄어쓰기가 바른 것은?",
    "passage": null,
    "choices": [
      { "id": "1", "text": "오빠가 운동한다" },
      { "id": "2", "text": "오빠 가운동한다" },
      { "id": "3", "text": "오빠가운동한다" },
      { "id": "4", "text": "오 빠가운동한다" }
    ],
    "answerId": "1",
    "timeLimitSec": 15
  },
  {
    "id": "saussure-gram-056",
    "serverId": "saussure",
    "questionType": "QUIZ",
    "category": "문법",
    "stem": "'지금 몇 시예요'는 어떤 문장인가?",
    "passage": null,
    "choices": [
      { "id": "1", "text": "알려 주는 문장" },
      { "id": "2", "text": "묻는 문장" },
      { "id": "3", "text": "시키는 문장" },
      { "id": "4", "text": "놀라는 문장" }
    ],
    "answerId": "2",
    "timeLimitSec": 15
  },
  {
    "id": "saussure-gram-057",
    "serverId": "saussure",
    "questionType": "QUIZ",
    "category": "문법",
    "stem": "바르게 쓴 문장은?",
    "passage": null,
    "choices": [
      { "id": "1", "text": "할머니가주무신다" },
      { "id": "2", "text": "할머 니가주무신다" },
      { "id": "3", "text": "할머니 가주무신다" },
      { "id": "4", "text": "할머니가 주무신다" }
    ],
    "answerId": "4",
    "timeLimitSec": 15
  },
  {
    "id": "saussure-gram-058",
    "serverId": "saussure",
    "questionType": "QUIZ",
    "category": "문법",
    "stem": "'드디어 이겼다'에 알맞은 부호는?",
    "passage": null,
    "choices": [
      { "id": "1", "text": "드디어 이겼다." },
      { "id": "2", "text": "드디어 이겼다?" },
      { "id": "3", "text": "드디어 이겼다!" },
      { "id": "4", "text": "드디어 이겼다," }
    ],
    "answerId": "3",
    "timeLimitSec": 15
  },
  {
    "id": "saussure-gram-059",
    "serverId": "saussure",
    "questionType": "QUIZ",
    "category": "문법",
    "stem": "띄어쓰기가 바른 것은?",
    "passage": null,
    "choices": [
      { "id": "1", "text": "꽃이예쁘다" },
      { "id": "2", "text": "꽃 이예쁘다" },
      { "id": "3", "text": "꽃이 예쁘다" },
      { "id": "4", "text": "꽃이예 쁘다" }
    ],
    "answerId": "3",
    "timeLimitSec": 15
  },
  {
    "id": "saussure-gram-060",
    "serverId": "saussure",
    "questionType": "QUIZ",
    "category": "문법",
    "stem": "'손을 깨끗이 씻으세요'는 어떤 문장인가?",
    "passage": null,
    "choices": [
      { "id": "1", "text": "묻는 문장" },
      { "id": "2", "text": "놀라는 문장" },
      { "id": "3", "text": "알려 주는 문장" },
      { "id": "4", "text": "시키는 문장" }
    ],
    "answerId": "4",
    "timeLimitSec": 15
  }
]