[
  {
    "title": "백학선전",
    "author": "작자미상",
    "hits_title": [
      "백학선전",
      "글로벌 세계 대백과사전/언어I·한국문학·논술/고려-조선의 문학/조선 후기 문학/소설문학의 발흥"
    ],
    "hits_title_author": [
      "글로벌 세계 대백과사전/언어I·한국문학·논술/고려-조선의 문학/조선 후기 문학/소설문학의 발흥"
    ]
  },
  {
    "title": "자경",
    "author": "박인로",
    "hits_title": [
      "자경",
      "진리편독삼자경",
      "농지법",
      "두시언해 (중간본)/권2/자경부봉선현영회",
      "대한민국 농지개혁법 (제31호)"
    ],
    "hits_title_author": [
      "자경",
      "조선왕조실록/태종공정대왕실록/17년",
      "조선왕조실록/태조강헌대왕실록/3년",
      "조선왕조실록/태종공정대왕실록/5년",
      "조선왕조실록/세종장헌대왕실록/1년"
    ]
  },
  {
    "title": "우리 동네 황씨",
    "author": "이문구",
    "hits_title": [
      "은세계",
      "정총대",
      "상록수/제14장",
      "흙/제4장",
      "흙/제2장"
    ],
    "hits_title_author": [
      "글로벌 세계 대백과사전/언어I·한국문학·논술/현대 문학/현대 후기 문학/60년대의 문학",
      "글로벌 세계 대백과사전/인명사전/한 국 인 명/ㅇ"
    ]
  },
  {
    "title": "눈길",
    "author": "고은",
    "hits_title": [
      "빙화/밤의 시름",
      "청춘극장/1권/30장",
      "2022년 제5회 국무회의 모두발언",
      "애인/35장",
      "불행한 계승"
    ],
    "hits_title_author": []
  },
  {
    "title": "세상에서 가장 아름다운 이별",
    "author": "노희경",
    "hits_title": [
      "오뇌의 무도/오뇌의 무도",
      "오뇌의 무도/베를렌의 시",
      "쌍녀분전기",
      "음악만필/쇼팽과 그의 연인",
      "음악만필/베토벤과 불후의 총자"
    ],
    "hits_title_author": []
  },
  {
    "title": "적벽가",
    "author": "작자미상",
    "hits_title": [
      "적벽가",
      "글로벌 세계 대백과사전/한국음악/한국음악/한국음악가/판소리의 명창",
      "글로벌 세계 대백과사전/한국음악/한국음악/한국음악의 종류/판소리",
      "글로벌 세계 대백과사전/문화·민속/한국의 연극/판 소 리/판소리의 명창",
      "글로벌 세계 대백과사전/문화·민속/한국의 연극/판 소 리/판소리의 창본"
    ],
    "hits_title_author": []
  },
  {
    "title": "김가성론",
    "author": "김성한",
    "hits_title": [
      "글로벌 세계 대백과사전/언어I·한국문학·논술/아시아 문학/중국 문학/근대·현대",
      "글로벌 세계 대백과사전/동양사상/동양의 사상/중국의 사상/송·명의 사상",
      "글로벌 세계 대백과사전/동양사상/한국의 사상/조선후기의 사상/조선후기의 철학사상",
      "조선왕조실록/광해군일기태백산본/5년",
      "글로벌 세계 대백과사전/종교·철학/세계의 종교/불 교/불교의 사상"
    ],
    "hits_title_author": [
      "글로벌 세계 대백과사전/인명사전/한 국 인 명/ㄱ"
    ]
  },
  {
    "title": "접동새",
    "author": "김소월",
    "hits_title": [
      "진달래꽃 (시집)/접동새",
      "조선여류한시선집/춘수",
      "진달래꽃 (시집)",
      "정과정",
      "글로벌 세계 대백과사전/언어I·한국문학·논술/고려-조선의 문학/조선 후기 문학/사설시조와 가집의 편찬"
    ],
    "hits_title_author": [
      "진달래꽃 (시집)/접동새",
      "진달래꽃 (시집)"
    ]
  },
  {
    "title": "미스터 방",
    "author": "채만식",
    "hits_title": [
      "미스터 방",
      "청춘극장/2권/60장",
      "청춘극장/3권/46장",
      "청춘극장/2권/48장",
      "청춘극장/2권/59장"
    ],
    "hits_title_author": [
      "미스터 방"
    ]
  },
  {
    "title": "시집살이 노래",
    "author": "작자미상",
    "hits_title": [
      "글로벌 세계 대백과사전/언어I·한국문학·논술/고려-조선의 문학/조선 후기 문학/가사의 성행",
      "해동염사/산유화가와 박향랑",
      "치악산/상권",
      "경희",
      "글로벌 세계 대백과사전/언어I·한국문학·논술/현대 문학/현대 전기 문학/근대 문예사조와 본격 문학기"
    ],
    "hits_title_author": [
      "글로벌 세계 대백과사전/언어I·한국문학·논술/고려-조선의 문학/조선 후기 문학/가사의 성행",
      "글로벌 세계 대백과사전/언어I·한국문학·논술/현대 문학/현대 전기 문학/근대 문예사조와 본격 문학기"
    ]
  },
  {
    "title": "구운몽",
    "author": "김만중",
    "hits_title": [
      "구운몽",
      "글로벌 세계 대백과사전/언어I·한국문학·논술/고려-조선의 문학/조선 후기 문학/소설문학의 발흥",
      "글로벌 세계 대백과사전/언어I·한국문학·논술/고려-조선의 문학/조선 후기 문학/조선 후기의 문학〔개설〕",
      "글로벌 세계 대백과사전/동양사상/한국의 사상/조선후기의 사상/조선후기의 문예사상",
      "글로벌 세계 대백과사전/한국사/근대사회의 태동/사회변화와 대외관계/실학의 발생"
    ],
    "hits_title_author": [
      "구운몽",
      "글로벌 세계 대백과사전/동양사상/한국의 사상/조선후기의 사상/조선후기의 문예사상",
      "글로벌 세계 대백과사전/언어I·한국문학·논술/고려-조선의 문학/조선 후기 문학/조선 후기의 문학〔개설〕",
      "글로벌 세계 대백과사전/언어I·한국문학·논술/고려-조선의 문학/조선 후기 문학/소설문학의 발흥",
      "글로벌 세계 대백과사전/언어I·한국문학·논술/고려-조선의 문학/조선 후기 문학/한문학과 실학파"
    ]
  },
  {
    "title": "조웅전",
    "author": "작자미상",
    "hits_title": [
      "조웅전",
      "나의 유년 시절",
      "글로벌 세계 대백과사전/언어I·한국문학·논술/고려-조선의 문학/조선 후기 문학/조선 후기의 문학〔개설〕",
      "글로벌 세계 대백과사전/동양사상/한국의 사상/조선전기의 사상/조선전기의 문예사상",
      "글로벌 세계 대백과사전/언어I·한국문학·논술/고려-조선의 문학/조선 후기 문학/소설문학의 발흥"
    ],
    "hits_title_author": [
      "조웅전",
      "글로벌 세계 대백과사전/언어I·한국문학·논술/고려-조선의 문학/조선 후기 문학/소설문학의 발흥",
      "글로벌 세계 대백과사전/동양사상/한국의 사상/조선전기의 사상/조선전기의 문예사상"
    ]
  },
  {
    "title": "만세전",
    "author": "염상섭",
    "hits_title": [
      "국경의 밤/영탄",
      "마의태자/제12장",
      "개역간이국한문한글판/하박국",
      "글로벌 세계 대백과사전/언어I·한국문학·논술/현대 문학/현대 전기 문학/근대 문예사조와 본격 문학기",
      "개역간이국한문한글판/고린도전서"
    ],
    "hits_title_author": [
      "글로벌 세계 대백과사전/언어I·한국문학·논술/현대 문학/현대 전기 문학/근대 문예사조와 본격 문학기"
    ]
  },
  {
    "title": "안락국전",
    "author": "작자미상",
    "hits_title": [
      "안락국전",
      "도산 안창호"
    ],
    "hits_title_author": [
      "도산 안창호"
    ]
  },
  {
    "title": "무지개는 언제 뜨는가",
    "author": "윤흥길",
    "hits_title": [
      "쌍무지개 뜨는 언덕/01장",
      "쌍무지개 뜨는 언덕/47장",
      "쌍무지개 뜨는 언덕",
      "대동강은 속삭인다",
      "쌍무지개 뜨는 언덕/19장"
    ],
    "hits_title_author": [
      "글로벌 세계 대백과사전/인명사전/한 국 인 명/ㅇ",
      "글로벌 세계 대백과사전/언어I·한국문학·논술/문학사 연표",
      "글로벌 세계 대백과사전/언어I·한국문학·논술/문학사 연표/자료"
    ]
  },
  {
    "title": "사냥",
    "author": "이태준",
    "hits_title": [
      "사냥",
      "청춘극장/2권",
      "글로벌 세계 대백과사전/컴퓨터·환경·첨단·지구과학/환 경/인류의 환경파괴/멸종 위기에 놓인 생물",
      "청춘극장/2권/40장",
      "글로벌 세계 대백과사전/한국미술/한국미술의 흐름/고구려의 미술/고구려의 회화"
    ],
    "hits_title_author": [
      "글로벌 세계 대백과사전/언어I·한국문학·논술/현대 문학/현대 전기 문학/근대 문예사조와 본격 문학기",
      "글로벌 세계 대백과사전/언어I·한국문학·논술/문학사 연표",
      "글로벌 세계 대백과사전/언어I·한국문학·논술/문학사 연표/자료"
    ]
  },
  {
    "title": "최척전",
    "author": "조위한",
    "hits_title": [
      "최척전"
    ],
    "hits_title_author": [
      "최척전"
    ]
  },
  {
    "title": "이춘풍전",
    "author": "작자미상",
    "hits_title": [
      "이춘풍전",
      "이춘풍전 (국립한글박물관)",
      "글로벌 세계 대백과사전/한국사/근대사회의 태동/문화의 새 기운/서민예술",
      "글로벌 세계 대백과사전/한국음악/한국음악/한국음악의 종류/판소리",
      "글로벌 세계 대백과사전/언어I·한국문학·논술/고려-조선의 문학/조선 후기 문학/소설문학의 발흥"
    ],
    "hits_title_author": [
      "글로벌 세계 대백과사전/언어I·한국문학·논술/고려-조선의 문학/조선 후기 문학/소설문학의 발흥"
    ]
  },
  {
    "title": "두 파산",
    "author": "염상섭",
    "hits_title": [
      "채무자 회생 및 파산에 관한 법률",
      "파산법 (대한민국)",
      "채무자 회생 및 파산에 관한 법률 (제9346호)",
      "채무자 회생 및 파산에 관한 법률 (제8863호)",
      "글로벌 세계 대백과사전/법률/민사소송법/파산법"
    ],
    "hits_title_author": [
      "문단 30년의 자취",
      "글로벌 세계 대백과사전/언어I·한국문학·논술/현대 문학/현대 후기 문학/현대 후기의 문학〔개설〕",
      "글로벌 세계 대백과사전/언어I·한국문학·논술/현대 문학/현대 후기 문학/과도기의 문학",
      "글로벌 세계 대백과사전/언어I·한국문학·논술/현대 문학/현대 전기 문학/근대 문예사조와 본격 문학기",
      "글로벌 세계 대백과사전/한국지리/중부지방-남부지방/대구광역시"
    ]
  },
  {
    "title": "사씨남정기",
    "author": "김만중",
    "hits_title": [
      "글로벌 세계 대백과사전/동양사상/한국의 사상/조선후기의 사상/조선후기의 문예사상",
      "글로벌 세계 대백과사전/문화·민속/한국의 연극/창 극/창극의 창우",
      "글로벌 세계 대백과사전/언어I·한국문학·논술/고려-조선의 문학/조선 후기 문학/조선 후기의 문학〔개설〕",
      "글로벌 세계 대백과사전/언어I·한국문학·논술/고려-조선의 문학/조선 후기 문학/소설문학의 발흥",
      "글로벌 세계 대백과사전/문화·민속/한국의 연극/한국의 신파극/신파극의 작가와 작품"
    ],
    "hits_title_author": [
      "글로벌 세계 대백과사전/동양사상/한국의 사상/조선후기의 사상/조선후기의 문예사상",
      "글로벌 세계 대백과사전/언어I·한국문학·논술/고려-조선의 문학/조선 후기 문학/조선 후기의 문학〔개설〕",
      "글로벌 세계 대백과사전/언어I·한국문학·논술/고려-조선의 문학/조선 후기 문학/소설문학의 발흥",
      "글로벌 세계 대백과사전/언어I·한국문학·논술/고려-조선의 문학/조선 후기 문학/한문학과 실학파",
      "글로벌 세계 대백과사전/한국사/근세사회의 발전/조선의 성립과 발전/조선 왕조의 경제·사회적 구조"
    ]
  },
  {
    "title": "원미동 시인",
    "author": "양귀자",
    "hits_title": [
      "글로벌 세계 대백과사전/언어I·한국문학·논술/현대 문학/현대 후기 문학/80년대의 문학"
    ],
    "hits_title_author": [
      "글로벌 세계 대백과사전/언어I·한국문학·논술/현대 문학/현대 후기 문학/80년대의 문학"
    ]
  },
  {
    "title": "흥부전",
    "author": "작자미상",
    "hits_title": [
      "흥부전",
      "흥부전 (경판 25장본)",
      "탁류/제3장",
      "글로벌 세계 대백과사전/언어I·한국문학·논술/현대 문학/현대 전기 문학/구극과 신극",
      "탁류"
    ],
    "hits_title_author": [
      "글로벌 세계 대백과사전/언어I·한국문학·논술/현대 문학/현대 전기 문학/개화사조와 신소설"
    ]
  },
  {
    "title": "금방울전",
    "author": "작자미상",
    "hits_title": [
      "금방울전",
      "글로벌 세계 대백과사전/언어I·한국문학·논술/고려-조선의 문학/조선 후기 문학/소설문학의 발흥"
    ],
    "hits_title_author": [
      "글로벌 세계 대백과사전/언어I·한국문학·논술/고려-조선의 문학/조선 후기 문학/소설문학의 발흥"
    ]
  },
  {
    "title": "천변풍경",
    "author": "박태원",
    "hits_title": [
      "글로벌 세계 대백과사전/한국음악/한국음악/한국음악의 종류/판소리",
      "글로벌 세계 대백과사전/언어I·한국문학·논술/고려-조선의 문학/조선 전기 문학/가사 문학",
      "단발",
      "글로벌 세계 대백과사전/언어I·한국문학·논술/현대 문학/현대 전기 문학/근대 문예사조와 본격 문학기",
      "글로벌 세계 대백과사전/세계미술/서양미술의 흐름/르네상스의 미술/이탈리아 르네상스의 조각"
    ],
    "hits_title_author": [
      "글로벌 세계 대백과사전/언어I·한국문학·논술/현대 문학/현대 전기 문학/근대 문예사조와 본격 문학기"
    ]
  },
  {
    "title": "역마",
    "author": "김동리",
    "hits_title": [
      "글로벌 세계 대백과사전/언어I·한국문학·논술/현대 문학/현대 후기 문학/과도기의 문학",
      "가외가전",
      "글로벌 세계 대백과사전/통상·산업/산업의 경영형태/서비스산업의 경영형태/통신업의 경영형태",
      "치악산/상권",
      "글로벌 세계 대백과사전/예술·스포츠·취미/영화/영화의 기초지식/한국영화의 역사"
    ],
    "hits_title_author": [
      "글로벌 세계 대백과사전/언어I·한국문학·논술/현대 문학/현대 후기 문학/과도기의 문학",
      "글로벌 세계 대백과사전/언어I·한국문학·논술/현대 문학/현대 전기 문학/근대 문예사조와 본격 문학기"
    ]
  },
  {
    "title": "머슴대길이",
    "author": "고은",
    "hits_title": [
      "일설 춘향전",
      "그의 자서전"
    ],
    "hits_title_author": [
      "일설 춘향전"
    ]
  },
  {
    "title": "즐거운 나의 집",
    "author": "신경림",
    "hits_title": [
      "즐거운 학문",
      "집",
      "글로벌 세계 대백과사전/세계음악/서양음악의 종류/외국민요",
      "동인사담집 2/조신의 꿈",
      "음악만필/이별의 소야곡"
    ],
    "hits_title_author": [
      "글로벌 세계 대백과사전/언어I·한국문학·논술/현대 문학/현대 후기 문학/80년대의 문학"
    ]
  },
  {
    "title": "선한 나무",
    "author": "유치환",
    "hits_title": [
      "개역한글판/베드로전서",
      "개역한글판/로마서",
      "개역한글판/디모데후서",
      "글로벌 세계 대백과사전/세계미술/서양미술의 흐름/중 세 미 술/초기 그리스도교의 미술",
      "개역한글판/미가"
    ],
    "hits_title_author": []
  },
  {
    "title": "섬진강 1",
    "author": "김용택",
    "hits_title": [
      "영산강·섬진강수계 물관리 및 주민지원 등에 관한 법률",
      "영산강·섬진강수계관리위원회규정",
      "영산강·섬진강수계 물관리 및 주민지원 등에 관한 법률 시행령",
      "영산강·섬진강수계 물관리 및 주민지원 등에 관한 법률 시행규칙",
      "글로벌 세계 대백과사전/한국지리/한국지리의 개요/한국의 지질과 지형/하 천"
    ],
    "hits_title_author": [
      "글로벌 세계 대백과사전/언어I·한국문학·논술/현대 문학/현대 후기 문학/80년대의 문학"
    ]
  },
  {
    "title": "향현",
    "author": "박두신",
    "hits_title": [
      "역어유해 (정자)/祭祀",
      "역어유해/祭祀",
      "심상소학일본역사보충교재교수참고서/권2/9. 대원군의 집정",
      "글로벌 세계 대백과사전/인명사전/한 국 인 명/ㅂ",
      "글로벌 세계 대백과사전/사회 I·문화재/문 화 재/중요 문화재/전라북도"
    ],
    "hits_title_author": [
      "글로벌 세계 대백과사전/한국사/근세사회의 발전/양반사회와 경제생활/양반관료의 대립과 분열"
    ]
  },
  {
    "title": "우리가 물이 되어",
    "author": "강은교",
    "hits_title": [
      "참된 어머니가 되어 주소서",
      "이 꼴이 되다니",
      "물",
      "글로벌 세계 대백과사전/생물I·동물·인체/동물의 분류/척 추 동 물/양서류",
      "우리 시의 방향"
    ],
    "hits_title_author": [
      "글로벌 세계 대백과사전/언어I·한국문학·논술/현대 문학/현대 후기 문학/70년대의 문학",
      "글로벌 세계 대백과사전/언어I·한국문학·논술/문학사 연표",
      "글로벌 세계 대백과사전/언어I·한국문학·논술/문학사 연표/자료"
    ]
  },
  {
    "title": "눈",
    "author": "박이문",
    "hits_title": [
      "눈",
      "진달래꽃 (시집)/오시는 눈",
      "하늘과 바람과 별과 시 (1955년)/눈",
      "눈 내리는 날",
      "해파리의 노래/눈 1"
    ],
    "hits_title_author": []
  },
  {
    "title": "추천사",
    "author": "서정주",
    "hits_title": [
      "국회예산정책처장추천위원회 및 국회입법조사처장추천위원회 구성 등에 관한 규칙",
      "난설헌집",
      "조선독립의 당위성 외",
      "외국인 서훈 추천에 관한 규칙",
      "검찰총장후보추천위원회 운영규정"
    ],
    "hits_title_author": [
      "글로벌 세계 대백과사전/언어I·한국문학·논술/현대 문학/현대 후기 문학/전후 문학의 전개",
      "글로벌 세계 대백과사전/언어I·한국문학·논술/현대 문학/현대 후기 문학/과도기의 문학",
      "글로벌 세계 대백과사전/언어I·한국문학·논술/현대 문학/현대 전기 문학/근대 문예사조와 본격 문학기",
      "글로벌 세계 대백과사전/인명사전/한 국 인 명/ㅅ",
      "글로벌 세계 대백과사전/인명사전/한 국 인 명/ㅈ"
    ]
  },
  {
    "title": "땅끝",
    "author": "나희덕",
    "hits_title": [
      "땅 속으로",
      "해파리의 노래/유랑의 노래",
      "개역한글판/이사야",
      "개역한글판/다니엘",
      "개역한글판/예레미야"
    ],
    "hits_title_author": []
  },
  {
    "title": "병원",
    "author": "윤동주",
    "hits_title": [
      "국립대학병원 설치법",
      "서울대학교병원 설치법",
      "국립대학치과병원 설치법",
      "국립소록도병원 운영규칙",
      "서울대학교치과병원 설치법"
    ],
    "hits_title_author": [
      "하늘과 바람과 별과 시 (1955년)/병원",
      "하늘과 바람과 별과 시 (1948년)/병원",
      "하늘과 바람과 별과 시 (1955년)/위로",
      "하늘과 바람과 별과 시 (1948년)/위로",
      "하늘과 바람과 별과 시 (1955년)"
    ]
  },
  {
    "title": "나무",
    "author": "박목월",
    "hits_title": [
      "향수/나무",
      "소나무재선충병 방제특별법",
      "진달래꽃 (시집)/바다가 변하야 뽕나무밭 된다고",
      "하늘과 바람과 별과 시 (1979년)/나무",
      "삭풍은 나무 끝에 불고"
    ],
    "hits_title_author": [
      "글로벌 세계 대백과사전/언어I·한국문학·논술/현대 문학/현대 후기 문학/과도기의 문학",
      "글로벌 세계 대백과사전/언어I·한국문학·논술/현대 문학/현대 후기 문학/전후 문학의 전개",
      "글로벌 세계 대백과사전/언어I·한국문학·논술/현대 문학/현대 전기 문학/근대 문예사조와 본격 문학기",
      "글로벌 세계 대백과사전/인명사전/한 국 인 명/ㅂ",
      "글로벌 세계 대백과사전/시사/현대사회와 시사/사회·환경·학술·문화/학술·문화"
    ]
  },
  {
    "title": "두만강 너 우리 강아",
    "author": "이용악",
    "hits_title": [
      "낡은 집",
      "국경의 밤/국경의 밤",
      "북국점경",
      "배시황전",
      "글로벌 세계 대백과사전/예술·스포츠·취미/영화/영화의 감상/한국영화의 감독과 작품"
    ],
    "hits_title_author": [
      "낡은 집",
      "글로벌 세계 대백과사전/언어I·한국문학·논술/현대 문학/현대 전기 문학/근대 문예사조와 본격 문학기"
    ]
  },
  {
    "title": "눈",
    "author": "김수영",
    "hits_title": [
      "눈",
      "진달래꽃 (시집)/오시는 눈",
      "하늘과 바람과 별과 시 (1955년)/눈",
      "눈 내리는 날",
      "해파리의 노래/눈 1"
    ],
    "hits_title_author": [
      "글로벌 세계 대백과사전/언어I·한국문학·논술/현대 문학/현대 후기 문학/60년대의 문학",
      "글로벌 세계 대백과사전/언어I·한국문학·논술/현대 문학/현대 후기 문학/80년대의 문학",
      "글로벌 세계 대백과사전/언어I·한국문학·논술/현대 문학/현대 후기 문학/전후 문학의 전개",
      "글로벌 세계 대백과사전/동양사상/한국의 사상/한국의 현대사상/한국의 현대 문예사상",
      "영원의 미소"
    ]
  },
  {
    "title": "무국어",
    "author": "조지훈",
    "hits_title": [
      "국어기본법",
      "국어기본법 (법률 제9491호, 대한민국)",
      "국어기본법 (법률 제10584호, 대한민국)",
      "국어기본법 (법률 제11424호, 대한민국)",
      "국어기본법 (법률 제9003호, 대한민국)"
    ],
    "hits_title_author": [
      "글로벌 세계 대백과사전/언어I·한국문학·논술/현대 문학/현대 전기 문학/근대 문예사조와 본격 문학기",
      "글로벌 세계 대백과사전/인명사전/한 국 인 명/ㅈ",
      "글로벌 세계 대백과사전/언어I·한국문학·논술/현대 문학/현대 후기 문학/70년대의 문학",
      "글로벌 세계 대백과사전/인명사전/한 국 인 명/ㅂ",
      "글로벌 세계 대백과사전/시사/현대사회와 시사/사회·환경·학술·문화/학술·문화"
    ]
  },
  {
    "title": "구름의 파수병",
    "author": "김수영",
    "hits_title": [
      "선화공주",
      "글로벌 세계 대백과사전/세계미술/서양미술의 흐름/르네상스의 미술/이탈리아 르네상스의 회화",
      "마의태자/제12장",
      "황원행/제4부",
      "노마만리/제3부"
    ],
    "hits_title_author": []
  },
  {
    "title": "느낌 이 극락같은",
    "author": "이강백",
    "hits_title": [
      "글로벌 세계 대백과사전/한국미술/미 술 용 어/ㅈ",
      "글로벌 세계 대백과사전/사회 I·문화재/문 화 재/중요 문화재/강원도 (북한)",
      "글로벌 세계 대백과사전/사회 I·문화재/문 화 재/중요 문화재/충청남도",
      "동인사담집 3/고달산",
      "글로벌 세계 대백과사전/사회 I·문화재/문 화 재/중요 문화재/경상북도"
    ],
    "hits_title_author": []
  },
  {
    "title": "흰 바람벽이 있어",
    "author": "백석",
    "hits_title": [
      "무자리",
      "물",
      "경영",
      "그립은 흘긴 눈",
      "배따라기"
    ],
    "hits_title_author": [
      "맥",
      "탁류/제10장",
      "허생전 (이광수)"
    ]
  },
  {
    "title": "느티나무로부터",
    "author": "복효근",
    "hits_title": [
      "느티나무 신세 이야기",
      "사랑의 선물/꽃 속의 작은이",
      "천사",
      "청춘극장/3권/18장",
      "피리"
    ],
    "hits_title_author": []
  },
  {
    "title": "절망을 위하여",
    "author": "곽재구",
    "hits_title": [
      "이상의 문학의 한 모",
      "글로벌 세계 대백과사전/세계사상/서양의 사상/현대의 사상/실존주의",
      "하이디/제 13장",
      "글로벌 세계 대백과사전/세계사상/사 상 용 어/특정한 사상가와 관계가 깊은 용어",
      "우연의 기적"
    ],
    "hits_title_author": []
  },
  {
    "title": "마음의 태양",
    "author": "조지훈",
    "hits_title": [
      "마음의 의장",
      "현해탄/어린 태양이 말하되",
      "태양의 풍속/태양의 풍속",
      "벽공무한/5장",
      "태양의 풍속/꿈꾸는 진주여 바다로 가자"
    ],
    "hits_title_author": [
      "글로벌 세계 대백과사전/언어I·한국문학·논술/현대 문학/현대 후기 문학/전후 문학의 전개",
      "글로벌 세계 대백과사전/언어I·한국문학·논술/현대 문학/현대 전기 문학/근대 문예사조와 본격 문학기",
      "글로벌 세계 대백과사전/언어I·한국문학·논술/현대 문학/현대 후기 문학/70년대의 문학",
      "글로벌 세계 대백과사전/시사/현대사회와 시사/사회·환경·학술·문화/학술·문화",
      "글로벌 세계 대백과사전/인명사전/한 국 인 명/ㅈ"
    ]
  },
  {
    "title": "폭풍",
    "author": "정호승",
    "hits_title": [
      "폭풍우를 기다리는 마음",
      "흑방의 선물/폭풍우의 밤",
      "청춘극장/2권",
      "청춘극장/3권",
      "현해탄/암흑의 정신"
    ],
    "hits_title_author": []
  },
  {
    "title": "성묘",
    "author": "고은",
    "hits_title": [
      "산호림/성묘",
      "나 사는 곳/성묘하러 가는 길",
      "글로벌 세계 대백과사전/문화·민속/국경일-공휴일-기념일과 민속/명절과 놀이·음식/추 석",
      "글로벌 세계 대백과사전/한국음악/아시아음악/베트남음악",
      "가정의례준칙 (제15호)"
    ],
    "hits_title_author": [
      "조선왕조실록/영종지행순덕영모의열장의홍륜광인돈희체천건극성공신화대성광운개태기영요명순철건건곤녕익문선무희경현효대왕실록/33년",
      "조선왕조실록/정종문성무열성인장효대왕실록/19년",
      "조선왕조실록/정종문성무열성인장효대왕실록/16년",
      "조선왕조실록/광해군일기태백산본/14년",
      "조선왕조실록/정종문성무열성인장효대왕실록/18년"
    ]
  },
  {
    "title": "외할머니의 뒤안 툇마루",
    "author": "서정주",
    "hits_title": [],
    "hits_title_author": []
  },
  {
    "title": "정주성",
    "author": "백석",
    "hits_title": [
      "글로벌 세계 대백과사전/한국사/근대사회의 태동/종교의 새 기운/농민의 반란",
      "글로벌 세계 대백과사전/동양사상/한국의 사상/조선후기의 사상/조선후기의 정치사상",
      "글로벌 세계 대백과사전/사회 I·문화재/현대사회의 대중과 사상/현대의 농촌/현대사회와 농촌",
      "중학교 국사 (7차 교육과정)/Ⅵ. 조선 사회의 변동",
      "홍경래전"
    ],
    "hits_title_author": [
      "글로벌 세계 대백과사전/언어I·한국문학·논술/현대 문학/현대 전기 문학/근대 문예사조와 본격 문학기"
    ]
  },
  {
    "title": "목계장터",
    "author": "신경림",
    "hits_title": [],
    "hits_title_author": []
  },
  {
    "title": "소리의 빛",
    "author": "이청준",
    "hits_title": [
      "글로벌 세계 대백과사전/세계미술/미술의 기초/조형의 요소와 미의 조건/빛 깔",
      "글로벌 세계 대백과사전/수학·물리·화학·실험/물리/빛과 파동/빛의 간섭",
      "글로벌 세계 대백과사전/수학·물리·화학·실험/물리/소리와 파동/소 리",
      "피리/빛을 기리는 노래",
      "글로벌 세계 대백과사전/수학·물리·화학·실험/수학-물리-화학 용어"
    ],
    "hits_title_author": [
      "글로벌 세계 대백과사전/언어I·한국문학·논술/현대 문학/현대 후기 문학/70년대의 문학",
      "글로벌 세계 대백과사전/언어I·한국문학·논술/현대 문학/현대 후기 문학/60년대의 문학",
      "글로벌 세계 대백과사전/예술·스포츠·취미/영화/영화의 감상/한국영화의 감상",
      "글로벌 세계 대백과사전/인명사전/한 국 인 명/ㅇ",
      "글로벌 세계 대백과사전/언어I·한국문학·논술/문학사 연표"
    ]
  },
  {
    "title": "조그만 체험기",
    "author": "박완서",
    "hits_title": [
      "글로벌 세계 대백과사전/인명사전/세 계 인 명/ㅂ"
    ],
    "hits_title_author": []
  },
  {
    "title": "삼대",
    "author": "염상섭",
    "hits_title": [
      "님이 오마 하거늘",
      "애인/5장",
      "청춘극장/2권/57장",
      "글로벌 세계 대백과사전/동양사상/동양의 사상/일본의 사상/불교사상",
      "애인/14장"
    ],
    "hits_title_author": [
      "문단 30년의 자취",
      "글로벌 세계 대백과사전/동양사상/한국의 사상/한국의 현대사상/한국의 현대 문예사상",
      "글로벌 세계 대백과사전/언어I·한국문학·논술/문학 용어/문학상의 주의·사조",
      "글로벌 세계 대백과사전/언어I·한국문학·논술/현대 문학/현대 전기 문학/근대 문예사조와 본격 문학기",
      "글로벌 세계 대백과사전/언어I·한국문학·논술/현대 문학/현대 후기 문학/과도기의 문학"
    ]
  },
  {
    "title": "유자소전",
    "author": "이문구",
    "hits_title": [
      "글로벌 세계 대백과사전/세계사/인류 문화의 시작/헬레니즘 시대와 로마 제국/진의 중국 통일",
      "파한집/권하",
      "삼국사기/권50/견훤",
      "열하일기/황교문답",
      "열하일기/태학유관록"
    ],
    "hits_title_author": []
  },
  {
    "title": "독 짓는 늙은이",
    "author": "황순원",
    "hits_title": [
      "글로벌 세계 대백과사전/예술·스포츠·취미/영화/영화의 감상/한국영화의 감독과 작품",
      "이상한 샘물",
      "병풍 속에 그린 닭이",
      "병풍에 그린 닭이",
      "따라지"
    ],
    "hits_title_author": [
      "글로벌 세계 대백과사전/예술·스포츠·취미/영화/영화의 감상/한국영화의 감독과 작품",
      "글로벌 세계 대백과사전/예술·스포츠·취미/영화/영화의 감상/한국영화의 감상",
      "글로벌 세계 대백과사전/언어I·한국문학·논술/문학사 연표",
      "글로벌 세계 대백과사전/언어I·한국문학·논술/문학사 연표/자료"
    ]
  },
  {
    "title": "강",
    "author": "서정인",
    "hits_title": [
      "영산강·섬진강수계 물관리 및 주민지원 등에 관한 법률",
      "강 배",
      "낙동강수계 물관리 및 주민지원 등에 관한 법률",
      "강 건너간 노래",
      "영산강·섬진강수계관리위원회규정"
    ],
    "hits_title_author": [
      "글로벌 세계 대백과사전/언어I·한국문학·논술/현대 문학/현대 후기 문학/60년대의 문학",
      "글로벌 세계 대백과사전/인명사전/한 국 인 명/ㅅ",
      "글로벌 세계 대백과사전/언어I·한국문학·논술/현대 문학/현대 후기 문학/80년대의 문학",
      "글로벌 세계 대백과사전/언어I·한국문학·논술/문학사 연표",
      "글로벌 세계 대백과사전/언어I·한국문학·논술/문학사 연표/자료"
    ]
  },
  {
    "title": "시장과 전장",
    "author": "박경리",
    "hits_title": [
      "글로벌 세계 대백과사전/언어I·한국문학·논술/현대 문학/현대 후기 문학/60년대의 문학",
      "글로벌 세계 대백과사전/세계지리/세계의 여러 나라/독립국가연합·동유럽/폴란드",
      "2002도3131",
      "글로벌 세계 대백과사전/세계사/근대 유럽과 아시아/남북전쟁과 제국주의의 발전/러시아의 제국주의와 차리즘의 위기",
      "중국 농촌의 협상"
    ],
    "hits_title_author": [
      "글로벌 세계 대백과사전/언어I·한국문학·논술/현대 문학/현대 후기 문학/60년대의 문학",
      "글로벌 세계 대백과사전/언어I·한국문학·논술/현대 문학/현대 후기 문학/전후 문학의 전개",
      "글로벌 세계 대백과사전/인명사전/한 국 인 명/ㅂ",
      "글로벌 세계 대백과사전/인명사전/한 국 인 명/ㅇ",
      "글로벌 세계 대백과사전/언어I·한국문학·논술/문학사 연표"
    ]
  },
  {
    "title": "박씨전",
    "author": "작자미상",
    "hits_title": [
      "박씨전",
      "글로벌 세계 대백과사전/언어I·한국문학·논술/고려-조선의 문학/조선 후기 문학/소설문학의 발흥",
      "글로벌 세계 대백과사전/언어I·한국문학·논술/고려-조선의 문학/조선 후기 문학/한문학과 실학파"
    ],
    "hits_title_author": [
      "글로벌 세계 대백과사전/언어I·한국문학·논술/고려-조선의 문학/조선 후기 문학/소설문학의 발흥",
      "글로벌 세계 대백과사전/언어I·한국문학·논술/고려-조선의 문학/조선 후기 문학/한문학과 실학파"
    ]
  },
  {
    "title": "회색 눈사람",
    "author": "최윤",
    "hits_title": [
      "방황",
      "글로벌 세계 대백과사전/문화·민속/한국의 연극/한국의 가면극/한국 가면극의 가면",
      "글로벌 세계 대백과사전/문화·민속/한국의 연극/한국의 가면극/한국 가면극의 무대·의상·소도구",
      "글로벌 세계 대백과사전/생물I·동물·인체/동물의 분류/척 추 동 물/포유류",
      "그림"
    ],
    "hits_title_author": [
      "글로벌 세계 대백과사전/시사/현대사회와 시사/사회·환경·학술·문화/학술·문화",
      "조선왕조실록/태종공정대왕실록/11년"
    ]
  },
  {
    "title": "토지",
    "author": "박경리",
    "hits_title": [
      "공익사업을 위한 토지 등의 취득 및 보상에 관한 법률",
      "한국토지주택공사법",
      "토지이용규제 기본법",
      "공공토지의 비축에 관한 법률",
      "한국토지공사법"
    ],
    "hits_title_author": [
      "글로벌 세계 대백과사전/언어I·한국문학·논술/현대 문학/현대 후기 문학/전후 문학의 전개",
      "글로벌 세계 대백과사전/예술·스포츠·취미/방송극/텔레비전 드라마/한국의 텔레비전 드라마",
      "글로벌 세계 대백과사전/언어I·한국문학·논술/현대 문학/현대 후기 문학/80년대의 문학",
      "글로벌 세계 대백과사전/인명사전/한 국 인 명/ㅂ",
      "글로벌 세계 대백과사전/문화·민속/예능 연표/영화 연표"
    ]
  },
  {
    "title": "토지",
    "author": "이형우 각색 시나리오",
    "hits_title": [
      "공익사업을 위한 토지 등의 취득 및 보상에 관한 법률",
      "한국토지주택공사법",
      "토지이용규제 기본법",
      "공공토지의 비축에 관한 법률",
      "한국토지공사법"
    ],
    "hits_title_author": []
  },
  {
    "title": "큰 산",
    "author": "이호철",
    "hits_title": [
      "부동산 가격공시 및 감정평가에 관한 법률",
      "산 (이효석)",
      "붉은 산",
      "글로벌 세계 대백과사전/기술·통신/재료기술/무기재료기술/산과 알칼리",
      "글로벌 세계 대백과사전/생물I·동물·인체/동물의 몸과 계통/동물 분포의 성립/산 악"
    ],
    "hits_title_author": [
      "글로벌 세계 대백과사전/언어I·한국문학·논술/현대 문학/현대 후기 문학/전후 문학의 전개",
      "글로벌 세계 대백과사전/언어I·한국문학·논술/현대 문학/현대 후기 문학/60년대의 문학",
      "글로벌 세계 대백과사전/언어I·한국문학·논술/현대 문학/현대 후기 문학/70년대의 문학",
      "글로벌 세계 대백과사전/인명사전/한 국 인 명/ㅇ",
      "글로벌 세계 대백과사전/세계미술/미술사 연표"
    ]
  },
  {
    "title": "황만근은 이렇게 말했다",
    "author": "성석제",
    "hits_title": [
      "영웅기",
      "사기/권028",
      "주부전",
      "한국 야담 사화 전집 (차상찬)/장대에 스러진 별",
      "홍계월전 (한구000023)"
    ],
    "hits_title_author": []
  },
  {
    "title": "눈이 오면",
    "author": "임철우",
    "hits_title": [
      "진달래꽃 (시집)/오시는 눈",
      "눈이 오시네",
      "어제 오던 눈이",
      "송림에 눈이 오니",
      "하늘과 바람과 별과 시 (1955년)/눈오는 지도"
    ],
    "hits_title_author": [
      "글로벌 세계 대백과사전/언어I·한국문학·논술/현대 문학/현대 후기 문학/80년대의 문학",
      "글로벌 세계 대백과사전/언어I·한국문학·논술/문학사 연표",
      "글로벌 세계 대백과사전/언어I·한국문학·논술/문학사 연표/자료"
    ]
  },
  {
    "title": "불모지",
    "author": "차범석",
    "hits_title": [
      "작품 제3번",
      "이명박 대통령 제80차 라디오 인터넷 연설",
      "슬픈 이야기 (이상)",
      "북찬가",
      "글로벌 세계 대백과사전/문화·민속/한국의 연극/한국의 신극/아동극"
    ],
    "hits_title_author": [
      "글로벌 세계 대백과사전/문화·민속/한국의 연극/한국의 신극/신극의 연혁",
      "글로벌 세계 대백과사전/문화·민속/한국의 연극/한국의 신극/신극의 배우",
      "글로벌 세계 대백과사전/문화·민속/한국의 연극/한국의 신극/신극의 극작가·연출가·비평가",
      "글로벌 세계 대백과사전/인명사전/한 국 인 명/ㅊ",
      "글로벌 세계 대백과사전/예술·스포츠·취미/예능 연표/연극 연표"
    ]
  },
  {
    "title": "월행",
    "author": "송기원",
    "hits_title": [
      "1959년 12월 31일 이전에 퇴직한 군인의 퇴직급여금지급에 관한 특별법",
      "소비생활용제품안전법 (2009년 (헤이세이 21년) 6월 5일 법률 제49호)",
      "1959년 12월 31일 이전에 퇴직한 군인의 퇴직급여금지급에 관한 특별법 (대한민국, 법률 제10820호)",
      "1959년 12월 31일 이전에 퇴직한 군인의 퇴직급여금지급에 관한 특별법 (대한민국, 법률 제8546호)",
      "글로벌 세계 대백과사전"
    ],
    "hits_title_author": [
      "글로벌 세계 대백과사전/언어I·한국문학·논술/현대 문학/현대 후기 문학/70년대의 문학",
      "글로벌 세계 대백과사전/언어I·한국문학·논술/문학사 연표",
      "글로벌 세계 대백과사전/언어I·한국문학·논술/문학사 연표/자료"
    ]
  },
  {
    "title": "쥐잡기",
    "author": "김소진",
    "hits_title": [],
    "hits_title_author": []
  },
  {
    "title": "탐내는 하꼬방",
    "author": "염상섭",
    "hits_title": [],
    "hits_title_author": []
  },
  {
    "title": "한계령",
    "author": "양귀자",
    "hits_title": [
      "군정법령 제144호",
      "조선왕조실록/세종장헌대왕실록/오례",
      "글로벌 세계 대백과사전/동양사상/한국의 사상/한국의 근대사상/한국의 근대 정치사상",
      "글로벌 세계 대백과사전/한국지리/중부지방-남부지방/강원도",
      "글로벌 세계 대백과사전/동양사상/동양의 사상/중국의 사상/송·명의 사상"
    ],
    "hits_title_author": []
  },
  {
    "title": "말을 찾아서",
    "author": "이순원",
    "hits_title": [
      "아기네/아버지를 찾아서",
      "무희의 봄을 찾아서",
      "새말의 이모저모",
      "글로벌 세계 대백과사전/세계사/현대 세계의 새 질서/유엔과 전후의 세계/평화에의 길을 찾아서",
      "동생을 찾으러"
    ],
    "hits_title_author": [
      "박근혜 정부의 문화예술계 블랙리스트",
      "글로벌 세계 대백과사전/언어I·한국문학·논술/문학사 연표",
      "글로벌 세계 대백과사전/언어I·한국문학·논술/문학사 연표/자료"
    ]
  },
  {
    "title": "공동 경비 구역 JSA",
    "author": "박상연 원작·박찬욱 각색",
    "hits_title": [
      "글로벌 세계 대백과사전/문화·민속/예능 연표/영화 연표",
      "글로벌 세계 대백과사전/예술·스포츠·취미/예능 연표/영화 연표",
      "글로벌 세계 대백과사전/예술·스포츠·취미/예능 연표/영화 연표 자료"
    ],
    "hits_title_author": []
  },
  {
    "title": "비 오는 길",
    "author": "최명익",
    "hits_title": [
      "백록담/비 (산문)",
      "비",
      "성암의 길",
      "동인사담집 1/눈 오는 대궐",
      "길놀이"
    ],
    "hits_title_author": [
      "글로벌 세계 대백과사전/언어I·한국문학·논술/현대 문학/현대 전기 문학/근대 문예사조와 본격 문학기"
    ]
  },
  {
    "title": "순이삼촌",
    "author": "현기영",
    "hits_title": [
      "선풍시대/5장",
      "동인사담집 5/신문고",
      "글로벌 세계 대백과사전/언어I·한국문학·논술/현대 문학/현대 후기 문학/80년대의 문학",
      "동생을 찾으러",
      "문재인 대통령 4.3희생자 추념일 추념사"
    ],
    "hits_title_author": [
      "문재인 대통령 4.3희생자 추념일 추념사",
      "글로벌 세계 대백과사전/언어I·한국문학·논술/현대 문학/현대 후기 문학/80년대의 문학"
    ]
  },
  {
    "title": "오발탄",
    "author": "이범선 원작·이종기 각색",
    "hits_title": [
      "글로벌 세계 대백과사전/언어I·한국문학·논술/현대 문학/현대 후기 문학/전후 문학의 전개",
      "글로벌 세계 대백과사전/예술·스포츠·취미/영화/영화의 감상/한국영화의 감독과 작품",
      "글로벌 세계 대백과사전/예술·스포츠·취미/방송극/라디오 드라마/한국의 성우",
      "글로벌 세계 대백과사전/예술·스포츠·취미/영화/영화의 기초지식/한국영화의 역사",
      "글로벌 세계 대백과사전/예술·스포츠·취미/영화/영화의 감상/한국영화의 감상"
    ],
    "hits_title_author": [
      "글로벌 세계 대백과사전/예술·스포츠·취미/영화/영화의 감상/한국영화의 감상"
    ]
  },
  {
    "title": "고풍 의상",
    "author": "조지훈",
    "hits_title": [
      "글로벌 세계 대백과사전/사회 I·문화재/문 화 재/중요 문화재/경상북도",
      "글로벌 세계 대백과사전/세계지리/세계의 여러 나라/아시아/타 이",
      "글로벌 세계 대백과사전/언어I·한국문학·논술/현대 문학/현대 전기 문학/근대 문예사조와 본격 문학기",
      "글로벌 세계 대백과사전/인명사전/한 국 인 명/ㅈ",
      "고문진보언해/권2"
    ],
    "hits_title_author": [
      "글로벌 세계 대백과사전/언어I·한국문학·논술/현대 문학/현대 전기 문학/근대 문예사조와 본격 문학기",
      "글로벌 세계 대백과사전/인명사전/한 국 인 명/ㅈ"
    ]
  },
  {
    "title": "성산별곡",
    "author": "정철",
    "hits_title": [
      "송강가사/셩산별곡",
      "글로벌 세계 대백과사전/언어I·한국문학·논술/고려-조선의 문학/조선 전기 문학/가사 문학",
      "글로벌 세계 대백과사전/언어I·한국문학·논술/고려-조선의 문학/조선 전기 문학/조선 전기의 문학〔개설〕",
      "글로벌 세계 대백과사전/동양사상/한국의 사상/조선전기의 사상/조선전기의 문예사상",
      "글로벌 세계 대백과사전/사회 I·문화재/문 화 재/중요 문화재/전라남도"
    ],
    "hits_title_author": [
      "송강가사/셩산별곡",
      "글로벌 세계 대백과사전/언어I·한국문학·논술/고려-조선의 문학/조선 전기 문학/가사 문학",
      "글로벌 세계 대백과사전/언어I·한국문학·논술/고려-조선의 문학/조선 전기 문학/조선 전기의 문학〔개설〕",
      "글로벌 세계 대백과사전/동양사상/한국의 사상/조선전기의 사상/조선전기의 문예사상",
      "글로벌 세계 대백과사전/한국사/근세사회의 발전/임진왜란과 병자호란/양반문화의 융성"
    ]
  },
  {
    "title": "몽천요",
    "author": "윤선도",
    "hits_title": [
      "몽천요",
      "글로벌 세계 대백과사전/언어I·한국문학·논술/고려-조선의 문학/조선 후기 문학/사설시조와 가집의 편찬"
    ],
    "hits_title_author": [
      "몽천요",
      "글로벌 세계 대백과사전/언어I·한국문학·논술/고려-조선의 문학/조선 후기 문학/사설시조와 가집의 편찬"
    ]
  },
  {
    "title": "명월음",
    "author": "최현",
    "hits_title": [
      "동의보감/집례",
      "고왕경",
      "쳔디팔양신쥬경",
      "만언사",
      "금방울전"
    ],
    "hits_title_author": []
  },
  {
    "title": "동동",
    "author": "작자미상",
    "hits_title": [
      "동동",
      "글로벌 세계 대백과사전/한국음악/한국음악/한국음악사/고려시대의 음악",
      "피리/가을",
      "글로벌 세계 대백과사전/문화·민속/한국의 연극/한국의 고전극/한국의 고전극〔서설〕",
      "글로벌 세계 대백과사전/한국음악/한국음악/한국음악사/조선 후기의 음악"
    ],
    "hits_title_author": [
      "간밤의 대취하고",
      "조웅전",
      "사랑의 선물",
      "글로벌 세계 대백과사전/언어I·한국문학·논술/고려-조선의 문학/조선 후기 문학/소설문학의 발흥",
      "글로벌 세계 대백과사전/언어I·한국문학·논술/아시아 문학/일본 문학/중세 전기(가마쿠라 시대)"
    ]
  },
  {
    "title": "가시리",
    "author": "작자미상",
    "hits_title": [
      "가시리",
      "글로벌 세계 대백과사전/한국음악/한국음악/한국음악사/고려시대의 음악",
      "글로벌 세계 대백과사전/언어I·한국문학·논술/삼국-통일신라의 문학/한국 문학의 성격과 특질",
      "글로벌 세계 대백과사전/언어I·한국문학·논술/고려-조선의 문학/고려시대 문학/고려시대의 문학〔개설〕",
      "글로벌 세계 대백과사전/언어I·한국문학·논술/문학 용어/한국 문학 용어"
    ],
    "hits_title_author": [
      "글로벌 세계 대백과사전/언어I·한국문학·논술/고려-조선의 문학/고려시대 문학/고려 후기",
      "글로벌 세계 대백과사전/언어I·한국문학·논술/고려-조선의 문학/조선 전기 문학/조선 전기 문학의 특성",
      "글로벌 세계 대백과사전/동양사상/한국의 사상/조선전기의 사상/조선전기의 문예사상",
      "글로벌 세계 대백과사전/언어I·한국문학·논술/현대 문학/현대 전기 문학/근대 문예사조와 본격 문학기"
    ]
  },
  {
    "title": "누항사",
    "author": "박인로",
    "hits_title": [
      "누항사",
      "글로벌 세계 대백과사전/언어I·한국문학·논술/고려-조선의 문학/조선 후기 문학/가사의 성행",
      "글로벌 세계 대백과사전/언어I·한국문학·논술/고려-조선의 문학/조선 후기 문학/조선 후기의 문학〔개설〕",
      "글로벌 세계 대백과사전/언어I·한국문학·논술/고려-조선의 문학/조선 전기 문학/가사 문학"
    ],
    "hits_title_author": [
      "누항사",
      "글로벌 세계 대백과사전/언어I·한국문학·논술/고려-조선의 문학/조선 후기 문학/가사의 성행",
      "글로벌 세계 대백과사전/언어I·한국문학·논술/고려-조선의 문학/조선 후기 문학/조선 후기의 문학〔개설〕",
      "글로벌 세계 대백과사전/언어I·한국문학·논술/고려-조선의 문학/조선 전기 문학/가사 문학"
    ]
  },
  {
    "title": "방음시여",
    "author": "신흠",
    "hits_title": [],
    "hits_title_author": []
  },
  {
    "title": "도산십이곡",
    "author": "이황",
    "hits_title": [
      "도산십이곡",
      "글로벌 세계 대백과사전/언어I·한국문학·논술/고려-조선의 문학/조선 전기 문학/시조 문학",
      "글로벌 세계 대백과사전/언어I·한국문학·논술/고려-조선의 문학/조선 전기 문학/조선 전기의 문학〔개설〕",
      "글로벌 세계 대백과사전/언어I·한국문학·논술/문학사 연표",
      "글로벌 세계 대백과사전/언어I·한국문학·논술/문학사 연표/자료"
    ],
    "hits_title_author": [
      "도산십이곡",
      "글로벌 세계 대백과사전/언어I·한국문학·논술/고려-조선의 문학/조선 전기 문학/시조 문학",
      "글로벌 세계 대백과사전/언어I·한국문학·논술/문학사 연표",
      "글로벌 세계 대백과사전/언어I·한국문학·논술/문학사 연표/자료"
    ]
  },
  {
    "title": "어부사시사",
    "author": "윤선도",
    "hits_title": [
      "어부사시사",
      "글로벌 세계 대백과사전/언어I·한국문학·논술/고려-조선의 문학/조선 후기 문학/사설시조와 가집의 편찬",
      "글로벌 세계 대백과사전/언어I·한국문학·논술/고려-조선의 문학/조선 후기 문학/조선 후기의 문학〔개설〕",
      "글로벌 세계 대백과사전/동양사상/한국의 사상/조선전기의 사상/조선전기의 문예사상",
      "글로벌 세계 대백과사전/한국사/근세사회의 발전/임진왜란과 병자호란/양반문화의 융성"
    ],
    "hits_title_author": [
      "어부사시사",
      "글로벌 세계 대백과사전/언어I·한국문학·논술/고려-조선의 문학/조선 후기 문학/사설시조와 가집의 편찬",
      "글로벌 세계 대백과사전/언어I·한국문학·논술/고려-조선의 문학/조선 후기 문학/조선 후기의 문학〔개설〕",
      "글로벌 세계 대백과사전/동양사상/한국의 사상/조선전기의 사상/조선전기의 문예사상",
      "글로벌 세계 대백과사전/한국사/근세사회의 발전/임진왜란과 병자호란/양반문화의 융성"
    ]
  },
  {
    "title": "연행가",
    "author": "홍순학",
    "hits_title": [
      "글로벌 세계 대백과사전/언어I·한국문학·논술/고려-조선의 문학/조선 후기 문학/가사의 성행",
      "글로벌 세계 대백과사전/언어I·한국문학·논술/고려-조선의 문학/조선 후기 문학/조선 후기의 문학〔개설〕",
      "글로벌 세계 대백과사전/한국사/근대사회의 태동/종교의 새 기운/19세기 전반의 개혁사상",
      "연행록"
    ],
    "hits_title_author": [
      "글로벌 세계 대백과사전/언어I·한국문학·논술/고려-조선의 문학/조선 후기 문학/가사의 성행",
      "글로벌 세계 대백과사전/언어I·한국문학·논술/고려-조선의 문학/조선 후기 문학/조선 후기의 문학〔개설〕"
    ]
  },
  {
    "title": "입암이십구곡",
    "author": "박인로",
    "hits_title": [
      "가루지기 타령 성두본"
    ],
    "hits_title_author": []
  },
  {
    "title": "고완",
    "author": "이태준",
    "hits_title": [
      "2017년 조선법률가위원회 백서",
      "열하일기/황교문답",
      "이대봉전 (회동서관)",
      "용비어천가/순치본/권1-2",
      "현수문전"
    ],
    "hits_title_author": []
  },
  {
    "title": "사시가",
    "author": "황희",
    "hits_title": [
      "사시가",
      "마경초집언해/사시평화태과불급맥",
      "글로벌 세계 대백과사전/동양사상/동양의 사상/동양의 중세 교육사상/송·원의 교육",
      "글로벌 세계 대백과사전/동양사상/한국의 사상/조선전기의 사상/조선전기의 경제사상",
      "진달래꽃 (시집)/여수"
    ],
    "hits_title_author": [
      "사시가",
      "황운전",
      "초등대한역사/제4편 현세",
      "조선왕조실록/정종대왕실록/1년",
      "조선왕조실록/태조강헌대왕실록/6년"
    ]
  },
  {
    "title": "전원사시가",
    "author": "신계영",
    "hits_title": [
      "글로벌 세계 대백과사전/문화·민속/세계의 연극/서양의 고전극/르네상스의 연극",
      "글로벌 세계 대백과사전/언어I·한국문학·논술/고려-조선의 문학/조선 전기 문학/가사 문학",
      "글로벌 세계 대백과사전/한국사/민족의 독립운동/신문화운동과 3·1운동/신문화운동",
      "글로벌 세계 대백과사전/언어II·세계문학·논술/러시아-북동 유럽 문학/북유럽 문학",
      "글로벌 세계 대백과사전/세계음악/서양음악가와 작품감상/러시아"
    ],
    "hits_title_author": []
  },
  {
    "title": "오륜가",
    "author": "주세붕",
    "hits_title": [
      "오륜가",
      "오륜가 (박인로)",
      "글로벌 세계 대백과사전/언어I·한국문학·논술/고려-조선의 문학/조선 전기 문학/조선 전기 문학의 특성",
      "글로벌 세계 대백과사전/언어I·한국문학·논술/고려-조선의 문학/조선 후기 문학/가사의 성행",
      "글로벌 세계 대백과사전/언어I·한국문학·논술/고려-조선의 문학/조선 후기 문학/사설시조와 가집의 편찬"
    ],
    "hits_title_author": [
      "글로벌 세계 대백과사전/언어I·한국문학·논술/고려-조선의 문학/조선 전기 문학/가사 문학",
      "글로벌 세계 대백과사전/동양사상/한국의 사상/조선전기의 사상/조선전기의 문예사상",
      "글로벌 세계 대백과사전/한국지리/중부지방-남부지방/전라남도"
    ]
  },
  {
    "title": "차마설",
    "author": "이곡",
    "hits_title": [
      "글로벌 세계 대백과사전/동양사상/한국의 사상/통일신라시대의 사상/통일신라시대의 불교사상",
      "글로벌 세계 대백과사전/종교·철학/한국의 종교/한국의 불교/한국불교의 역사"
    ],
    "hits_title_author": []
  },
  {
    "title": "견회요",
    "author": "윤선도",
    "hits_title": [
      "견회요",
      "글로벌 세계 대백과사전/언어I·한국문학·논술/고려-조선의 문학/조선 후기 문학/사설시조와 가집의 편찬",
      "글로벌 세계 대백과사전/동양사상/한국의 사상/조선전기의 사상/조선전기의 문예사상"
    ],
    "hits_title_author": [
      "견회요",
      "글로벌 세계 대백과사전/언어I·한국문학·논술/고려-조선의 문학/조선 후기 문학/사설시조와 가집의 편찬",
      "글로벌 세계 대백과사전/동양사상/한국의 사상/조선전기의 사상/조선전기의 문예사상"
    ]
  },
  {
    "title": "만언사",
    "author": "안조원",
    "hits_title": [
      "만언사",
      "글로벌 세계 대백과사전/언어I·한국문학·논술/고려-조선의 문학/조선 후기 문학/가사의 성행"
    ],
    "hits_title_author": []
  },
  {
    "title": "덴동어미 화전가",
    "author": "작자미상",
    "hits_title": [],
    "hits_title_author": []
  },
  {
    "title": "비가",
    "author": "이정환",
    "hits_title": [
      "비를 다고",
      "파란 비",
      "민사소송비용법",
      "하늘과 바람과 별과 시 (1955년)/소낙비",
      "진달래꽃 (시집)/봄비"
    ],
    "hits_title_author": [
      "글로벌 세계 대백과사전/언어I·한국문학·논술/고려-조선의 문학/조선 후기 문학/사설시조와 가집의 편찬",
      "글로벌 세계 대백과사전/언어I·한국문학·논술/현대 문학/현대 후기 문학/70년대의 문학",
      "박근혜 정부의 문화예술계 블랙리스트",
      "홍경래전",
      "글로벌 세계 대백과사전/언어I·한국문학·논술/문학사 연표"
    ]
  },
  {
    "title": "풍란",
    "author": "이병기",
    "hits_title": [
      "98도1949",
      "향수/백록담",
      "글로벌 세계 대백과사전/생물II·식물·관찰/식물의 재배와 관찰/식물의 이용/원예식물",
      "글로벌 세계 대백과사전/생물II·식물·관찰/식물의 계통과 분류/속 씨 식 물/외떡잎식물",
      "글로벌 세계 대백과사전/컴퓨터·환경·첨단·지구과학/환 경/인류의 환경파괴/멸종 위기에 놓인 생물"
    ],
    "hits_title_author": []
  },
  {
    "title": "면앙정가",
    "author": "송순",
    "hits_title": [
      "면앙정가",
      "글로벌 세계 대백과사전/언어I·한국문학·논술/고려-조선의 문학/조선 전기 문학/가사 문학",
      "글로벌 세계 대백과사전/언어I·한국문학·논술/고려-조선의 문학/조선 전기 문학/조선 전기의 문학〔개설〕",
      "글로벌 세계 대백과사전/한국음악/한국음악/한국음악의 종류/가 사",
      "글로벌 세계 대백과사전/동양사상/한국의 사상/조선전기의 사상/조선전기의 문예사상"
    ],
    "hits_title_author": [
      "면앙정가",
      "글로벌 세계 대백과사전/언어I·한국문학·논술/고려-조선의 문학/조선 전기 문학/조선 전기의 문학〔개설〕",
      "글로벌 세계 대백과사전/언어I·한국문학·논술/고려-조선의 문학/조선 전기 문학/가사 문학",
      "글로벌 세계 대백과사전/동양사상/한국의 사상/조선전기의 사상/조선전기의 문예사상",
      "글로벌 세계 대백과사전/시사/현대사회와 시사/사회·환경·학술·문화/학술·문화"
    ]
  },
  {
    "title": "강호구가",
    "author": "나위소",
    "hits_title": [
      "글로벌 세계 대백과사전/언어I·한국문학·논술/아시아 문학/일본 문학/중세 후기(무로마치 시대)",
      "글로벌 세계 대백과사전/언어I·한국문학·논술/아시아 문학/중국 문학/당·송시대",
      "글로벌 세계 대백과사전/인명사전/한 국 인 명/ㅁ",
      "심상소학일본역사보충교재교수참고서/권2/6. 임진란",
      "글로벌 세계 대백과사전/언어I·한국문학·논술/아시아 문학/일본 문학/근 대"
    ],
    "hits_title_author": [
      "심청전",
      "가루지기 타령 성두본",
      "보통교과 동국역사/권4",
      "흥보가 신재효본"
    ]
  },
  {
    "title": "용추유영가",
    "author": "정훈",
    "hits_title": [
      "조선왕조실록/태조강헌대왕실록/7년"
    ],
    "hits_title_author": []
  },
  {
    "title": "강호연군가",
    "author": "장경세",
    "hits_title": [
      "글로벌 세계 대백과사전/언어I·한국문학·논술/고려-조선의 문학/조선 전기 문학/시조 문학"
    ],
    "hits_title_author": [
      "글로벌 세계 대백과사전/언어I·한국문학·논술/고려-조선의 문학/조선 전기 문학/시조 문학"
    ]
  }
]