{
  "contentId": "8eeb1fac-1cb9-40d0-8fe3-5d25dd3b6c2a",
  "contentType": "READING_NONFICTION_RECALL",
  "version": 1,
  "status": "PUBLISHED",
  "title": "비문학 복기 학습 01",
  "description": "요약 카드를 순서대로 배열",
  "targetLevel": "RUSSELL_1",
  "schoolGradeRange": {
    "min": 4,
    "max": 6
  },
  "area": "READING",
  "subArea": "NONFICTION_PHILOSOPHY",
  "competencies": [
    "VOCAB",
    "READING"
  ],
  "tags": [],
  "access": {
    "mode": "FREE"
  },
  "seedReward": {
    "seedType": "WHEAT",
    "count": 3,
    "multiplier": 1
  },
  "timeLimitSec": 180,
  "assets": {},
  "payload": {
    "cards": [
      {
        "id": "c1",
        "text": "질문은 사유의 출발이다"
      },
      {
        "id": "c2",
        "text": "질문의 형태가 사고를 결정한다"
      },
      {
        "id": "c3",
        "text": "정교한 질문이 깊이를 만든다"
      }
    ],
    "correctOrder": [
      "c1",
      "c2",
      "c3"
    ],
    "seedPool": {
      "initial": 3,
      "wrongPenaltySeed": 1
    }
  }
}