{
  "contentId": "dq-s2-035",
  "contentType": "DAILY_QUIZ",
  "title": "일일 퀴즈 - 소쉬르2 Day 35",
  "description": "소쉬르 2단계 35일차 퀴즈",
  "targetLevel": "SAUSSURE_2",
  "area": "VOCAB",
  "subArea": "DAILY",
  "competencies": [
    "COMPREHENSIVE"
  ],
  "tags": [
    "daily",
    "mixed"
  ],
  "seedReward": {
    "seedType": "WHEAT",
    "count": 3,
    "multiplier": 1
  },
  "timeLimitSec": 180,
  "payload": {
    "pageStack": true,
    "layout": "EXAM_SHEET",
    "questions": [
      {
        "id": "dq-s2-035-1",
        "type": "MULTI_CHOICE",
        "questionKind": "WORD_TO_MEANING",
        "competency": "어휘력",
        "passage": "날씨가 좋아서 가족과 함께 '나들이'를 갔습니다.",
        "stem": "'나들이'의 뜻으로 알맞은 것은 무엇인가요?",
        "choices": [
          {
            "id": "A",
            "text": "집을 떠나 가까운 곳에 잠시 다녀오는 일"
          },
          {
            "id": "B",
            "text": "먼 나라로 이사 가는 일"
          },
          {
            "id": "C",
            "text": "집에서 하루 종일 잠자는 일"
          },
          {
            "id": "D",
            "text": "학교에서 공부하는 일"
          }
        ],
        "answerId": "A",
        "explanation": "'나들이'는 기분 전환을 위해 가까운 곳으로 잠시 외출하는 것을 뜻해요. 소풍과 비슷해요.",
        "scoring": {
          "correctDeltaSec": 10,
          "wrongDeltaSec": 0
        }
      },
      {
        "id": "dq-s2-035-2",
        "type": "MULTI_CHOICE",
        "questionKind": "READING_COMPREHENSION",
        "competency": "문장 독해력",
        "passage": "공원으로 소풍을 왔습니다. 돗자리를 펴고 도시락을 먹었습니다. 나무 그늘 아래에서 시원한 바람을 맞으며 쉬었습니다.",
        "stem": "공원에서 한 일이 아닌 것은?",
        "choices": [
          {
            "id": "A",
            "text": "돗자리 펴기"
          },
          {
            "id": "B",
            "text": "도시락 먹기"
          },
          {
            "id": "C",
            "text": "쉬기"
          },
          {
            "id": "D",
            "text": "수영하기"
          }
        ],
        "answerId": "D",
        "explanation": "글에서 돗자리 펴기, 도시락 먹기, 쉬기는 나왔지만 수영하기는 나오지 않았어요.",
        "scoring": {
          "correctDeltaSec": 10,
          "wrongDeltaSec": 0
        }
      },
      {
        "id": "dq-s2-035-3",
        "type": "MULTI_CHOICE",
        "questionKind": "STRUCTURE_READING",
        "competency": "구조 독해력",
        "passage": "즐거운 봄 소풍을 다녀왔습니다. 아침 일찍 김밥을 준비했습니다. 차를 타고 공원에 도착했습니다. 재미있게 놀다가 집으로 돌아왔습니다.",
        "stem": "이 글은 어떤 순서로 쓰였나요?",
        "choices": [
          {
            "id": "A",
            "text": "시간이 흐른 순서"
          },
          {
            "id": "B",
            "text": "장소의 크기 순서"
          },
          {
            "id": "C",
            "text": "중요한 내용 순서"
          },
          {
            "id": "D",
            "text": "거꾸로 된 순서"
          }
        ],
        "answerId": "A",
        "explanation": "아침 준비부터 공원 도착, 집으로 돌아옴까지 시간의 흐름에 따라 쓴 글이에요.",
        "scoring": {
          "correctDeltaSec": 10,
          "wrongDeltaSec": 0
        }
      },
      {
        "id": "dq-s2-035-4",
        "type": "MULTI_CHOICE",
        "questionKind": "BACKGROUND_KNOWLEDGE",
        "competency": "배경지식",
        "passage": "이것은 소풍 갈 때 음식을 담아 가는 통입니다. 밥, 반찬, 김밥, 과일 등을 넣어서 다닙니다.",
        "stem": "이것은 무엇인가요?",
        "choices": [
          {
            "id": "A",
            "text": "쓰레기통"
          },
          {
            "id": "B",
            "text": "도시락"
          },
          {
            "id": "C",
            "text": "필통"
          },
          {
            "id": "D",
            "text": "저금통"
          }
        ],
        "answerId": "B",
        "explanation": "나들이 갈 때 음식을 싸 가지고 다니는 그릇을 '도시락'이라고 해요.",
        "scoring": {
          "correctDeltaSec": 10,
          "wrongDeltaSec": 0
        }
      },
      {
        "id": "dq-s2-035-5",
        "type": "MULTI_CHOICE",
        "questionKind": "INFERENCE",
        "competency": "추론",
        "passage": "공원에서 놀다가 돌아갈 시간이 되었습니다. 영희는 자꾸만 뒤를 돌아봅니다. 발걸음이 떨어지지 않습니다.",
        "stem": "영희의 마음은 어떨까요?",
        "choices": [
          {
            "id": "A",
            "text": "집에 빨리 가고 싶어서 신난다."
          },
          {
            "id": "B",
            "text": "더 놀고 싶어서 아쉽다."
          },
          {
            "id": "C",
            "text": "배가 고파서 힘들다."
          },
          {
            "id": "D",
            "text": "무서워서 도망치고 싶다."
          }
        ],
        "answerId": "B",
        "explanation": "뒤를 돌아보고 발걸음이 떨어지지 않는 행동에서 아쉬운 마음을 읽을 수 있어요.",
        "scoring": {
          "correctDeltaSec": 10,
          "wrongDeltaSec": 0
        }
      },
      {
        "id": "dq-s2-035-6",
        "type": "MULTI_CHOICE",
        "questionKind": "CRITICAL_THINKING",
        "competency": "비판적 사고",
        "passage": "A: \"먹고 남은 쓰레기는 귀찮으니까 풀숲에 버리고 가자.\"\nB: \"아니야. '가져온 쓰레기는 다시 가져가기'가 공원 이용 규칙이야.\"",
        "stem": "누구의 행동이 공중도덕을 잘 지키는 것인가요?",
        "choices": [
          {
            "id": "A",
            "text": "A"
          },
          {
            "id": "B",
            "text": "B"
          },
          {
            "id": "C",
            "text": "둘 다 그렇다"
          },
          {
            "id": "D",
            "text": "둘 다 아니다"
          }
        ],
        "answerId": "B",
        "explanation": "공공장소에서는 발생한 쓰레기를 되가져가거나 지정된 곳에 버려야 해요. B가 옳아요.",
        "scoring": {
          "correctDeltaSec": 10,
          "wrongDeltaSec": 0
        }
      },
      {
        "id": "dq-s2-035-7",
        "type": "MULTI_CHOICE",
        "questionKind": "CREATIVE_THINKING",
        "competency": "창의적 사고",
        "passage": "\"봄 소풍은 우리 가족에게 주는 __________________.\"",
        "stem": "봄 소풍의 즐거움을 비유한 표현은?",
        "choices": [
          {
            "id": "A",
            "text": "달콤한 선물 같아요"
          },
          {
            "id": "B",
            "text": "숙제 같아요"
          },
          {
            "id": "C",
            "text": "벌청소 같아요"
          },
          {
            "id": "D",
            "text": "짐 같아요"
          }
        ],
        "answerId": "A",
        "explanation": "가족과 함께하는 즐거운 소풍은 행복을 주는 '달콤한 선물'과 같아요.",
        "scoring": {
          "correctDeltaSec": 10,
          "wrongDeltaSec": 0
        }
      },
      {
        "id": "dq-s2-035-8",
        "type": "MULTI_CHOICE",
        "questionKind": "PROBLEM_SOLVING",
        "competency": "문제 해결",
        "passage": "넓은 공원에서 잠시 한눈을 팔다가 엄마, 아빠를 잃어버렸어요.",
        "stem": "이때 어떻게 해야 할까요?",
        "choices": [
          {
            "id": "A",
            "text": "급해서 이곳저곳을 뛰어다니며 엄마, 아빠를 찾는다."
          },
          {
            "id": "B",
            "text": "제자리에 멈춰 서서 기다리며 경찰관이나 안내원에게 도움을 청한다."
          },
          {
            "id": "C",
            "text": "누구든 보이는 사람을 따라가서 함께 찾아 달라고 한다."
          },
          {
            "id": "D",
            "text": "무서워서 숨어 버리고 아무에게도 말하지 않는다."
          }
        ],
        "answerId": "B",
        "explanation": "길을 잃었을 때는 당황하지 않고 제자리에 멈춰 있거나, 도움을 줄 수 있는 어른에게 요청해야 해요. 돌아다니면 찾기 더 힘들어요.",
        "scoring": {
          "correctDeltaSec": 10,
          "wrongDeltaSec": 0
        }
      },
      {
        "id": "dq-s2-035-9",
        "type": "SENTENCE_BUILDING",
        "questionKind": "SENTENCE_BUILDING",
        "stem": "다음 글을 읽고, 핵심을 한 문장으로 완성하세요.",
        "passage": "민지는 내일 할 일을 적었다.\n미리 준비하면 실수할 일이 줄어든다.",
        "correctSentence": "미리 준비하면 실수가 줄어든다.",
        "sentenceParts": [
          {
            "answer": "미리 준비하면",
            "distractors": [
              "대충 하면",
              "급하게 하면",
              "그대로 두면"
            ]
          },
          {
            "answer": "실수가",
            "distractors": [
              "그가",
              "우리는",
              "선생님이"
            ]
          },
          {
            "answer": "줄어든다.",
            "distractors": [
              "늘어난다.",
              "사라진다.",
              "바뀐다."
            ]
          }
        ],
        "scoring": {
          "correctDeltaSec": 10,
          "wrongDeltaSec": 0
        }
      },
      {
        "id": "dq-s2-035-10",
        "type": "MULTI_CHOICE",
        "questionKind": "GRAMMAR",
        "competency": "문법 또는 어법",
        "stem": "높임말을 바르게 사용한 문장은?",
        "choices": [
          {
            "id": "A",
            "text": "할머니, 밥 먹어."
          },
          {
            "id": "B",
            "text": "할머니, 진지 드세요."
          },
          {
            "id": "C",
            "text": "할머니, 밥 드세요."
          },
          {
            "id": "D",
            "text": "할머니, 진지 먹어."
          }
        ],
        "answerId": "B",
        "explanation": "어른께는 '밥' 대신 '진지', '먹다' 대신 '드시다'를 써야 해요.",
        "scoring": {
          "correctDeltaSec": 10,
          "wrongDeltaSec": 0
        }
      }
    ]
  }
}
