{
  "contentId": "dq-s2-126",
  "contentType": "DAILY_QUIZ",
  "title": "일일 퀴즈 - 소쉬르2 Day 126",
  "description": "소쉬르 2단계 126일차 퀴즈",
  "targetLevel": "SAUSSURE_2",
  "area": "VOCAB",
  "subArea": "DAILY",
  "competencies": [
    "COMPREHENSIVE"
  ],
  "tags": [
    "daily",
    "mixed"
  ],
  "seedReward": {
    "seedType": "WHEAT",
    "count": 3,
    "multiplier": 1
  },
  "timeLimitSec": 180,
  "payload": {
    "pageStack": true,
    "layout": "EXAM_SHEET",
    "questions": [
      {
        "id": "dq-s2-126-1",
        "type": "MULTI_CHOICE",
        "questionKind": "WORD_TO_MEANING",
        "competency": "어휘력",
        "passage": "안전 요원의 말씀을 잘 '따릅니다'.",
        "stem": "'따르다'의 뜻으로 알맞은 것은 무엇인가요?",
        "choices": [
          {
            "id": "A",
            "text": "남이 하라는 대로 하다"
          },
          {
            "id": "B",
            "text": "물을 컵에 붓다"
          },
          {
            "id": "C",
            "text": "뒤에서 쫓아가다"
          },
          {
            "id": "D",
            "text": "좋아하다"
          }
        ],
        "answerId": "A",
        "explanation": "여기서 '따르다'는 규칙이나 지시 등을 그대로 실행한다는 뜻이에요.",
        "scoring": {
          "correctDeltaSec": 10,
          "wrongDeltaSec": 0
        }
      },
      {
        "id": "dq-s2-126-2",
        "type": "MULTI_CHOICE",
        "questionKind": "READING_COMPREHENSION",
        "competency": "문장 독해력",
        "passage": "물놀이는 재미있지만 위험할 수도 있습니다. 너무 깊은 곳에 가지 말고 어른들과 함께 놀아야 합니다.",
        "stem": "물놀이를 안전하게 하는 방법은?",
        "choices": [
          {
            "id": "A",
            "text": "깊은 곳에 혼자 가기"
          },
          {
            "id": "B",
            "text": "어른들과 함께 얕은 곳에서 놀기"
          },
          {
            "id": "C",
            "text": "친구를 물에 빠뜨리기"
          },
          {
            "id": "D",
            "text": "준비 운동 안 하고 들어가기"
          }
        ],
        "answerId": "B",
        "explanation": "깊은 곳은 위험하므로 얕은 곳에서 보호자와 함께 노는 것이 안전해요.",
        "scoring": {
          "correctDeltaSec": 10,
          "wrongDeltaSec": 0
        }
      },
      {
        "id": "dq-s2-126-3",
        "type": "MULTI_CHOICE",
        "questionKind": "STRUCTURE_READING",
        "competency": "구조 독해력",
        "passage": "물놀이 용품. 1 튜브는 물에 둥둥 뜨게 해 줍니다. 2 물안경은 물속을 잘 볼 수 있게 해 줍니다. 3 오리발은 헤엄을 빨리 칠 수 있게 해 줍니다.",
        "stem": "물속을 볼 때 필요한 물건은?",
        "choices": [
          {
            "id": "A",
            "text": "튜브"
          },
          {
            "id": "B",
            "text": "물안경"
          },
          {
            "id": "C",
            "text": "오리발"
          },
          {
            "id": "D",
            "text": "수영복"
          }
        ],
        "answerId": "B",
        "explanation": "2번에서 물안경이 물속을 잘 볼 수 있게 해 준다고 했어요.",
        "scoring": {
          "correctDeltaSec": 10,
          "wrongDeltaSec": 0
        }
      },
      {
        "id": "dq-s2-126-4",
        "type": "MULTI_CHOICE",
        "questionKind": "BACKGROUND_KNOWLEDGE",
        "competency": "배경지식",
        "passage": "계곡이나 바다에서 물이 갑자기 깊어지는 곳이 있어 위험합니다.",
        "stem": "안전한 물놀이 장소가 아닌 곳은?",
        "choices": [
          {
            "id": "A",
            "text": "안전 요원이 있는 수영장"
          },
          {
            "id": "B",
            "text": "어린이 전용 풀장"
          },
          {
            "id": "C",
            "text": "깊이를 알 수 없는 저수지나 계곡 깊은 곳"
          },
          {
            "id": "D",
            "text": "얕은 개울가"
          }
        ],
        "answerId": "C",
        "explanation": "깊이를 알 수 없거나 갑자기 깊어지는 곳은 사고 위험이 매우 높아요.",
        "scoring": {
          "correctDeltaSec": 10,
          "wrongDeltaSec": 0
        }
      },
      {
        "id": "dq-s2-126-5",
        "type": "MULTI_CHOICE",
        "questionKind": "INFERENCE",
        "competency": "추론",
        "passage": "수영장에서 나온 영희가 배를 움켜쥐고 \"아이고 배야.\" 합니다. 점심에 찬 아이스크림을 3개나 먹었습니다.",
        "stem": "영희가 배가 아픈 이유는 무엇일까요?",
        "choices": [
          {
            "id": "A",
            "text": "수영을 너무 많이 해서"
          },
          {
            "id": "B",
            "text": "찬 음식을 너무 많이 먹어서 배탈"
          },
          {
            "id": "C",
            "text": "배가 고파서"
          },
          {
            "id": "D",
            "text": "물에 빠져서"
          }
        ],
        "answerId": "B",
        "explanation": "찬 음식을 과도하게 섭취하면 배탈이 날 수 있어요.",
        "scoring": {
          "correctDeltaSec": 10,
          "wrongDeltaSec": 0
        }
      },
      {
        "id": "dq-s2-126-6",
        "type": "MULTI_CHOICE",
        "questionKind": "CRITICAL_THINKING",
        "competency": "비판적 사고",
        "passage": "A: \"물놀이 후에는 몸을 깨끗이 씻어야 해.\"\nB: \"물속에 있었으니까 이미 깨끗해. 그냥 옷 입을래.\"",
        "stem": "누구의 생각이 위생적인가요?",
        "choices": [
          {
            "id": "A",
            "text": "A"
          },
          {
            "id": "B",
            "text": "B"
          },
          {
            "id": "C",
            "text": "둘 다 그렇다"
          },
          {
            "id": "D",
            "text": "둘 다 아니다"
          }
        ],
        "answerId": "A",
        "explanation": "수영장 물이나 바닷물에는 소독약품이나 세균이 있을 수 있으므로 깨끗한 물로 씻어야 해요.",
        "scoring": {
          "correctDeltaSec": 10,
          "wrongDeltaSec": 0
        }
      },
      {
        "id": "dq-s2-126-7",
        "type": "MULTI_CHOICE",
        "questionKind": "CREATIVE_THINKING",
        "competency": "창의적 사고",
        "passage": "\"첨벙첨벙 물장구는 시원한 __________________.\"",
        "stem": "물장구를 비유한 표현은?",
        "choices": [
          {
            "id": "A",
            "text": "물방울 춤 같아요"
          },
          {
            "id": "B",
            "text": "돌멩이 같아요"
          },
          {
            "id": "C",
            "text": "침대 같아요"
          },
          {
            "id": "D",
            "text": "조각상 같아요"
          }
        ],
        "answerId": "A",
        "explanation": "물이 튀는 모습이 마치 물방울들이 춤을 추는 것 같다고 비유할 수 있어요.",
        "scoring": {
          "correctDeltaSec": 10,
          "wrongDeltaSec": 0
        }
      },
      {
        "id": "dq-s2-126-8",
        "type": "MULTI_CHOICE",
        "questionKind": "PROBLEM_SOLVING",
        "competency": "문제 해결",
        "passage": "워터파크에서 엄마 손을 놓쳐서 길을 잃었어요.",
        "stem": "이때 어떻게 해야 할까요?",
        "choices": [
          {
            "id": "A",
            "text": "여기저기 뛰어다니며 엄마를 찾아다닌다."
          },
          {
            "id": "B",
            "text": "그 자리에 머물러 안내 데스크나 미아 보호소에 도움을 요청한다."
          },
          {
            "id": "C",
            "text": "혼자 출구 쪽으로 가서 엄마를 찾으려 한다."
          },
          {
            "id": "D",
            "text": "모르는 사람을 믿고 따라가 버린다."
          }
        ],
        "answerId": "B",
        "explanation": "돌아다니면 더 찾기 힘들어지므로 제자리에 있거나 안전 요원에게 도움을 청해야 해요.",
        "scoring": {
          "correctDeltaSec": 10,
          "wrongDeltaSec": 0
        }
      },
      {
        "id": "dq-s2-126-9",
        "type": "SENTENCE_BUILDING",
        "questionKind": "SENTENCE_BUILDING",
        "stem": "다음 글을 읽고, 핵심을 한 문장으로 완성하세요.",
        "passage": "하늘은 내일 할 일을 적었다.\n미리 준비하면 실수할 일이 줄어든다.",
        "correctSentence": "미리 준비하면 실수가 줄어든다.",
        "sentenceParts": [
          {
            "answer": "미리 준비하면",
            "distractors": [
              "나중에 준비하면",
              "급하게 하면",
              "대충 하면"
            ]
          },
          {
            "answer": "실수가",
            "distractors": [
              "선생님이",
              "이 글은",
              "우리는"
            ]
          },
          {
            "answer": "줄어든다.",
            "distractors": [
              "변한다.",
              "늘어난다.",
              "사라진다."
            ]
          }
        ],
        "scoring": {
          "correctDeltaSec": 10,
          "wrongDeltaSec": 0
        }
      },
      {
        "id": "dq-s2-126-10",
        "type": "MULTI_CHOICE",
        "questionKind": "GRAMMAR",
        "competency": "문법 또는 어법",
        "stem": "다음 낱말의 맞춤법이 바른 것은?",
        "choices": [
          {
            "id": "A",
            "text": "헤엄"
          },
          {
            "id": "B",
            "text": "해엄"
          },
          {
            "id": "C",
            "text": "회엄"
          },
          {
            "id": "D",
            "text": "휑엄"
          }
        ],
        "answerId": "A",
        "explanation": "물속에서 팔다리를 움직여 나아가는 짓은 '헤엄'이라고 해요.",
        "scoring": {
          "correctDeltaSec": 10,
          "wrongDeltaSec": 0
        }
      }
    ]
  }
}
