{
  "contentId": "dq-s2-140",
  "contentType": "DAILY_QUIZ",
  "title": "일일 퀴즈 - 소쉬르2 Day 140",
  "description": "소쉬르 2단계 140일차 퀴즈",
  "targetLevel": "SAUSSURE_2",
  "area": "VOCAB",
  "subArea": "DAILY",
  "competencies": [
    "COMPREHENSIVE"
  ],
  "tags": [
    "daily",
    "mixed"
  ],
  "seedReward": {
    "seedType": "WHEAT",
    "count": 3,
    "multiplier": 1
  },
  "timeLimitSec": 180,
  "payload": {
    "pageStack": true,
    "layout": "EXAM_SHEET",
    "questions": [
      {
        "id": "dq-s2-140-1",
        "type": "MULTI_CHOICE",
        "questionKind": "WORD_TO_MEANING",
        "competency": "어휘력",
        "passage": "방학 동안의 일을 '계획'합니다.",
        "stem": "'계획'의 뜻으로 알맞은 것은 무엇인가요?",
        "choices": [
          {
            "id": "A",
            "text": "앞으로 할 일을 미리 생각하여 정함"
          },
          {
            "id": "B",
            "text": "이미 지난 일을 후회함"
          },
          {
            "id": "C",
            "text": "아무것도 하지 않고 놂"
          },
          {
            "id": "D",
            "text": "잠만 잠"
          }
        ],
        "answerId": "A",
        "explanation": "'계획'은 미래의 일을 미리 구상하고 정하는 것을 말해요.",
        "scoring": {
          "correctDeltaSec": 10,
          "wrongDeltaSec": 0
        }
      },
      {
        "id": "dq-s2-140-2",
        "type": "MULTI_CHOICE",
        "questionKind": "READING_COMPREHENSION",
        "competency": "문장 독해력",
        "passage": "여름 방학이 되면 학교에 가지 않습니다. 부족했던 공부를 보충하거나 가족과 함께 여행을 갈 수 있습니다.",
        "stem": "여름 방학에 할 수 있는 일이 아닌 것은?",
        "choices": [
          {
            "id": "A",
            "text": "부족한 공부 하기"
          },
          {
            "id": "B",
            "text": "가족 여행 가기"
          },
          {
            "id": "C",
            "text": "친구와 놀기"
          },
          {
            "id": "D",
            "text": "매일 학교 가서 수업 듣기"
          }
        ],
        "answerId": "D",
        "explanation": "방학은 학교 수업을 쉬는 기간이므로 매일 학교에 가서 수업을 듣지는 않아요.",
        "scoring": {
          "correctDeltaSec": 10,
          "wrongDeltaSec": 0
        }
      },
      {
        "id": "dq-s2-140-3",
        "type": "MULTI_CHOICE",
        "questionKind": "STRUCTURE_READING",
        "competency": "구조 독해력",
        "passage": "나의 방학 계획. 1 매일 줄넘기를 할 것이다. 2 책을 10권 읽을 것이다. 3 밥을 아예 먹지 않을 것이다.",
        "stem": "건강한 방학 생활 계획이 아닌 것은?",
        "choices": [
          {
            "id": "A",
            "text": "1"
          },
          {
            "id": "B",
            "text": "2"
          },
          {
            "id": "C",
            "text": "3"
          },
          {
            "id": "D",
            "text": "모두 좋음"
          }
        ],
        "answerId": "C",
        "explanation": "밥을 먹지 않는 것은 건강을 해치는 일이므로 좋은 계획이 아니에요.",
        "scoring": {
          "correctDeltaSec": 10,
          "wrongDeltaSec": 0
        }
      },
      {
        "id": "dq-s2-140-4",
        "type": "MULTI_CHOICE",
        "questionKind": "BACKGROUND_KNOWLEDGE",
        "competency": "배경지식",
        "passage": "하루 동안 할 일을 시간 순서대로 둥근 원 모양의 표에 나타낸 것입니다.",
        "stem": "이것은 무엇인가요?",
        "choices": [
          {
            "id": "A",
            "text": "생활 계획표"
          },
          {
            "id": "B",
            "text": "달력"
          },
          {
            "id": "C",
            "text": "시계"
          },
          {
            "id": "D",
            "text": "지도"
          }
        ],
        "answerId": "A",
        "explanation": "하루 일과를 계획하여 나타낸 표를 '생활 계획표'라고 해요.",
        "scoring": {
          "correctDeltaSec": 10,
          "wrongDeltaSec": 0
        }
      },
      {
        "id": "dq-s2-140-5",
        "type": "MULTI_CHOICE",
        "questionKind": "INFERENCE",
        "competency": "추론",
        "passage": "매일 늦잠을 자고 텔레비전만 보던 철수가 개학 날이 되어 거울을 봤습니다. 얼굴이 푸석푸석하고 기운이 없어 보입니다.",
        "stem": "철수의 방학 생활은 어땠을까요?",
        "choices": [
          {
            "id": "A",
            "text": "규칙적이고 건강했다."
          },
          {
            "id": "B",
            "text": "불규칙하고 게을렀다."
          },
          {
            "id": "C",
            "text": "운동을 열심히 했다."
          },
          {
            "id": "D",
            "text": "공부를 너무 많이 했다."
          }
        ],
        "answerId": "B",
        "explanation": "늦잠과 TV 시청만 한 것으로 보아 게으르고 불규칙한 생활을 했음을 알 수 있어요.",
        "scoring": {
          "correctDeltaSec": 10,
          "wrongDeltaSec": 0
        }
      },
      {
        "id": "dq-s2-140-6",
        "type": "MULTI_CHOICE",
        "questionKind": "CRITICAL_THINKING",
        "competency": "비판적 사고",
        "passage": "A: \"방학이니까 늦게까지 자고 밤새도록 게임만 해도 돼.\"\nB: \"방학이라도 규칙적으로 생활해야 몸도 튼튼해지고 개학 후에도 힘들지 않아.\"",
        "stem": "누구의 생각이 건강한 생활인가요?",
        "choices": [
          {
            "id": "A",
            "text": "A"
          },
          {
            "id": "B",
            "text": "B"
          },
          {
            "id": "C",
            "text": "둘 다 그렇다"
          },
          {
            "id": "D",
            "text": "둘 다 아니다"
          }
        ],
        "answerId": "B",
        "explanation": "규칙적인 생활 습관을 유지하는 B의 태도가 건강에 좋아요.",
        "scoring": {
          "correctDeltaSec": 10,
          "wrongDeltaSec": 0
        }
      },
      {
        "id": "dq-s2-140-7",
        "type": "MULTI_CHOICE",
        "questionKind": "CREATIVE_THINKING",
        "competency": "창의적 사고",
        "passage": "\"여름 방학은 쑥쑥 자라나는 __________________.\"",
        "stem": "방학을 비유한 표현은?",
        "choices": [
          {
            "id": "A",
            "text": "키나무 같아요"
          },
          {
            "id": "B",
            "text": "작은 돌 같아요"
          },
          {
            "id": "C",
            "text": "멈춘 시계 같아요"
          },
          {
            "id": "D",
            "text": "빈 상자 같아요"
          }
        ],
        "answerId": "A",
        "explanation": "방학 동안 몸과 마음이 성장한다는 의미에서 '자라나는 나무'에 비유할 수 있어요.",
        "scoring": {
          "correctDeltaSec": 10,
          "wrongDeltaSec": 0
        }
      },
      {
        "id": "dq-s2-140-8",
        "type": "MULTI_CHOICE",
        "questionKind": "PROBLEM_SOLVING",
        "competency": "문제 해결",
        "passage": "방학 숙제가 너무 많아서 다 못 할 것 같아요.",
        "stem": "이때 어떻게 하면 좋을까요?",
        "choices": [
          {
            "id": "A",
            "text": "다 포기하고 안 한다."
          },
          {
            "id": "B",
            "text": "미리 계획을 세워 매일 조금씩 나누어 한다."
          },
          {
            "id": "C",
            "text": "개학 전날 밤새워서 대충 한다."
          },
          {
            "id": "D",
            "text": "엄마한테 해 달라고 조른다."
          }
        ],
        "answerId": "B",
        "explanation": "계획을 세워 꾸준히 실천하는 것이 가장 좋은 방법이에요.",
        "scoring": {
          "correctDeltaSec": 10,
          "wrongDeltaSec": 0
        }
      },
      {
        "id": "dq-s2-140-9",
        "type": "SENTENCE_BUILDING",
        "questionKind": "SENTENCE_BUILDING",
        "stem": "다음 글을 읽고, 핵심을 한 문장으로 완성하세요.",
        "passage": "현우는 내일 할 일을 적었다.\n미리 준비하면 실수할 일이 줄어든다.",
        "correctSentence": "미리 준비하면 실수가 줄어든다.",
        "sentenceParts": [
          {
            "answer": "미리 준비하면",
            "distractors": [
              "나중에 하면",
              "그대로 두면",
              "급하게 하면"
            ]
          },
          {
            "answer": "실수가",
            "distractors": [
              "사람들은",
              "우리는",
              "친구가"
            ]
          },
          {
            "answer": "줄어든다.",
            "distractors": [
              "변한다.",
              "늘어난다.",
              "멈춘다."
            ]
          }
        ],
        "scoring": {
          "correctDeltaSec": 10,
          "wrongDeltaSec": 0
        }
      },
      {
        "id": "dq-s2-140-10",
        "type": "MULTI_CHOICE",
        "questionKind": "GRAMMAR",
        "competency": "문법 또는 어법",
        "stem": "다음 문장의 빈칸에 알맞은 말은? \"공부를 _____.\"",
        "choices": [
          {
            "id": "A",
            "text": "할 것입니다."
          },
          {
            "id": "B",
            "text": "할 것임니다."
          },
          {
            "id": "C",
            "text": "할 거입니다."
          },
          {
            "id": "D",
            "text": "할 꺼입니다."
          }
        ],
        "answerId": "A",
        "explanation": "추측이나 의지를 나타내는 종결 어미 '-ㄹ 것이다 할 것입니다'가 바른 표기예요.",
        "scoring": {
          "correctDeltaSec": 10,
          "wrongDeltaSec": 0
        }
      }
    ]
  }
}
