{
  "contentId": "dq-s2-317",
  "contentType": "DAILY_QUIZ",
  "title": "일일 퀴즈 - 소쉬르2 Day 317",
  "description": "소쉬르 2단계 317일차 퀴즈",
  "targetLevel": "SAUSSURE_2",
  "area": "VOCAB",
  "subArea": "DAILY",
  "competencies": [
    "COMPREHENSIVE"
  ],
  "tags": [
    "daily",
    "social_studies"
  ],
  "seedReward": {
    "seedType": "WHEAT",
    "count": 3,
    "multiplier": 1
  },
  "timeLimitSec": 180,
  "payload": {
    "pageStack": true,
    "layout": "EXAM_SHEET",
    "questions": [
      {
        "id": "dq-s2-317-1",
        "type": "MULTI_CHOICE",
        "questionKind": "WORD_TO_MEANING",
        "competency": "어휘력",
        "passage": "여름철에 윙윙거리며 날아다니고 사람의 피를 빨아먹는 해충을 '모기'라고 합니다.",
        "stem": "'모기'는 어떤 곤충인가요?",
        "choices": [
          {
            "id": "A",
            "text": "사람의 피를 빨아먹는 해충"
          },
          {
            "id": "B",
            "text": "꽃가루를 옮겨 주는 익충"
          },
          {
            "id": "C",
            "text": "거미줄을 치고 사는 곤충"
          },
          {
            "id": "D",
            "text": "땅속에 집을 짓는 곤충"
          }
        ],
        "answerId": "A",
        "explanation": "모기는 사람이나 동물의 피를 빨아먹으며 병균을 옮기기도 하는 해로운 곤충 해충이에요.",
        "scoring": {
          "correctDeltaSec": 10,
          "wrongDeltaSec": 0
        }
      },
      {
        "id": "dq-s2-317-2",
        "type": "MULTI_CHOICE",
        "questionKind": "READING_COMPREHENSION",
        "competency": "문장 독해력",
        "passage": "모기에 물리면 가렵고 붓습니다. 침을 바르지 말고 약을 바르거나 찬물로 씻어야 합니다.",
        "stem": "모기에 물렸을 때 올바른 대처법은?",
        "choices": [
          {
            "id": "A",
            "text": "약을 바르거나 씻는다"
          },
          {
            "id": "B",
            "text": "침을 잔뜩 바른다"
          },
          {
            "id": "C",
            "text": "피가 날 때까지 벅벅 긁는다"
          },
          {
            "id": "D",
            "text": "반창고를 눈에 붙인다"
          }
        ],
        "answerId": "A",
        "explanation": "침에는 세균이 많아 상처가 덧날 수 있고, 긁으면 상처가 커지므로 약을 바르거나 차갑게 해 주는 게 좋아요.",
        "scoring": {
          "correctDeltaSec": 10,
          "wrongDeltaSec": 0
        }
      },
      {
        "id": "dq-s2-317-3",
        "type": "MULTI_CHOICE",
        "questionKind": "STRUCTURE_READING",
        "competency": "구조 독해력",
        "passage": "모기가 싫어하는 것. 1 모기향. 2 계피 냄새. 3 모기장. 4 땀 냄새.",
        "stem": "모기가 좋아하는 것은?",
        "choices": [
          {
            "id": "A",
            "text": "4"
          },
          {
            "id": "B",
            "text": "1"
          },
          {
            "id": "C",
            "text": "2"
          },
          {
            "id": "D",
            "text": "3"
          }
        ],
        "answerId": "A",
        "explanation": "모기는 사람의 땀 냄새나 숨 쉴 때 나오는 이산화탄소를 좋아해서 쫓아다녀요.",
        "scoring": {
          "correctDeltaSec": 10,
          "wrongDeltaSec": 0
        }
      },
      {
        "id": "dq-s2-317-4",
        "type": "MULTI_CHOICE",
        "questionKind": "BACKGROUND_KNOWLEDGE",
        "competency": "배경지식",
        "passage": "모기의 애벌레는 물속에서 삽니다. 이 애벌레를 '장구'처럼 생겼다고 하여 '이것'이라고 부릅니다.",
        "stem": "이것은 무엇인가요?",
        "choices": [
          {
            "id": "A",
            "text": "장구벌레"
          },
          {
            "id": "B",
            "text": "송충이"
          },
          {
            "id": "C",
            "text": "굼벵이"
          },
          {
            "id": "D",
            "text": "누에"
          }
        ],
        "answerId": "A",
        "explanation": "모기의 유충 애벌레은 물구나무를 선 채로 위아래로 움직이는 모습이 장구 칠 때의 채 놀림과 비슷하고 모양도 닮아서 장구벌레라고 해요.",
        "scoring": {
          "correctDeltaSec": 10,
          "wrongDeltaSec": 0
        }
      },
      {
        "id": "dq-s2-317-5",
        "type": "MULTI_CHOICE",
        "questionKind": "INFERENCE",
        "competency": "추론",
        "passage": "밤에 잘 때 '윙~' 하는 소리가 들리더니 다음 날 아침 팔다리에 울긋불긋한 자국이 생겼습니다.",
        "stem": "무슨 일이 있었나요?",
        "choices": [
          {
            "id": "A",
            "text": "모기에게 물렸다"
          },
          {
            "id": "B",
            "text": "호랑이에게 물렸다"
          },
          {
            "id": "C",
            "text": "그림을 그렸다"
          },
          {
            "id": "D",
            "text": "스티커를 붙였다"
          }
        ],
        "answerId": "A",
        "explanation": "'윙' 소리는 모기의 날갯짓 소리고, 울긋불긋하고 가려운 자국은 모기에 물린 흔적이에요.",
        "scoring": {
          "correctDeltaSec": 10,
          "wrongDeltaSec": 0
        }
      },
      {
        "id": "dq-s2-317-6",
        "type": "MULTI_CHOICE",
        "questionKind": "CRITICAL_THINKING",
        "competency": "비판적 사고",
        "passage": "A: \"물웅덩이를 그냥 두면 모기가 많이 생길 거야.\"\nB: \"모기가 알을 낳도록 물웅덩이를 더 많이 만들어야지.\"",
        "stem": "누구의 생각이 모기를 줄이는 데 도움이 되나요?",
        "choices": [
          {
            "id": "A",
            "text": "A"
          },
          {
            "id": "B",
            "text": "B"
          },
          {
            "id": "C",
            "text": "둘 다 도움이 된다"
          },
          {
            "id": "D",
            "text": "둘 다 도움이 되지 않는다"
          }
        ],
        "answerId": "A",
        "explanation": "모기는 고인 물에 알을 낳으므로 집 근처의 물웅덩이나 고인 물을 없애야 모기가 생기는 것을 막을 수 있어요.",
        "scoring": {
          "correctDeltaSec": 10,
          "wrongDeltaSec": 0
        }
      },
      {
        "id": "dq-s2-317-7",
        "type": "MULTI_CHOICE",
        "questionKind": "CREATIVE_THINKING",
        "competency": "창의적 사고",
        "passage": "\"살금살금 다가와 뾰족한 주사기를 꽂는 모기는 밤의 __________________.\"",
        "stem": "모기를 비유한 표현은?",
        "choices": [
          {
            "id": "A",
            "text": "불청객 의사 선생님 같아요"
          },
          {
            "id": "B",
            "text": "반가운 친구 같아요"
          },
          {
            "id": "C",
            "text": "예쁜 나비 같아요"
          },
          {
            "id": "D",
            "text": "귀여운 강아지 같아요"
          }
        ],
        "answerId": "A",
        "explanation": "허락도 없이 다가와 뾰족한 침 주사기을 찌르는 모습이 마치 초대받지 않은 의사 선생님 같아요.",
        "scoring": {
          "correctDeltaSec": 10,
          "wrongDeltaSec": 0
        }
      },
      {
        "id": "dq-s2-317-8",
        "type": "MULTI_CHOICE",
        "questionKind": "PROBLEM_SOLVING",
        "competency": "문제 해결",
        "passage": "캠핑을 갔는데 모기가 너무 많아요.",
        "stem": "모기에 물리지 않으려면?",
        "choices": [
          {
            "id": "A",
            "text": "긴 옷을 입고 모기 기피제를 뿌린다"
          },
          {
            "id": "B",
            "text": "옷을 다 벗고 잔다"
          },
          {
            "id": "C",
            "text": "불을 환하게 켜 놓고 잔다"
          },
          {
            "id": "D",
            "text": "설탕물을 몸에 바른다"
          }
        ],
        "answerId": "A",
        "explanation": "피부 노출을 줄이고 모기가 싫어하는 향을 피우거나 바르는 것이 예방에 도움이 돼요.",
        "scoring": {
          "correctDeltaSec": 10,
          "wrongDeltaSec": 0
        }
      },
      {
        "id": "dq-s2-317-9",
        "type": "SENTENCE_BUILDING",
        "questionKind": "SENTENCE_BUILDING",
        "stem": "다음 글을 읽고, 핵심을 한 문장으로 완성하세요.",
        "passage": "서연은 복도에서 뛰다 친구와 부딪힐 뻔했다.\n선생님은 복도에서는 천천히 걷자고 말했다.",
        "correctSentence": "복도에서는 천천히 걷는다.",
        "sentenceParts": [
          {
            "answer": "복도에서는",
            "distractors": [
              "집에서는",
              "교실에서는",
              "글쓴이는"
            ]
          },
          {
            "answer": "천천히",
            "distractors": [
              "작게",
              "조용히",
              "빠르게"
            ]
          },
          {
            "answer": "걷는다.",
            "distractors": [
              "뛴다.",
              "웃는다.",
              "간다."
            ]
          }
        ],
        "scoring": {
          "correctDeltaSec": 10,
          "wrongDeltaSec": 0
        }
      },
      {
        "id": "dq-s2-317-10",
        "type": "MULTI_CHOICE",
        "questionKind": "GRAMMAR",
        "competency": "문법 또는 어법",
        "stem": "다음 문장의 빈칸에 알맞은 말은? \"모기가 윙윙 _____.\"",
        "choices": [
          {
            "id": "A",
            "text": "거립니다"
          },
          {
            "id": "B",
            "text": "거림니다"
          },
          {
            "id": "C",
            "text": "꺼립니다"
          },
          {
            "id": "D",
            "text": "꺼림니다"
          }
        ],
        "answerId": "A",
        "explanation": "'거리다'의 활용형 '거립니다'가 바른 표기예요.",
        "scoring": {
          "correctDeltaSec": 10,
          "wrongDeltaSec": 0
        }
      }
    ]
  }
}
