{
  "contentId": "dq-s2-361",
  "contentType": "DAILY_QUIZ",
  "title": "일일 퀴즈 - 소쉬르2 Day 361",
  "description": "소쉬르 2단계 361일차 퀴즈",
  "targetLevel": "SAUSSURE_2",
  "area": "VOCAB",
  "subArea": "DAILY",
  "competencies": [
    "COMPREHENSIVE"
  ],
  "tags": [
    "daily",
    "arts"
  ],
  "seedReward": {
    "seedType": "WHEAT",
    "count": 3,
    "multiplier": 1
  },
  "timeLimitSec": 180,
  "payload": {
    "pageStack": true,
    "layout": "EXAM_SHEET",
    "questions": [
      {
        "id": "dq-s2-361-1",
        "type": "MULTI_CHOICE",
        "questionKind": "WORD_TO_MEANING",
        "competency": "어휘력",
        "passage": "추운 겨울에 붉게 피어나는 꽃으로, 잎이 두껍고 윤기가 나는 나무를 '동백나무'라고 합니다.",
        "stem": "'동백꽃'의 특징은?",
        "choices": [
          {
            "id": "A",
            "text": "겨울에 핌"
          },
          {
            "id": "B",
            "text": "여름에 핀다"
          },
          {
            "id": "C",
            "text": "보라색 꽃이다"
          },
          {
            "id": "D",
            "text": "잎이 얇고 잘 찢어진다"
          }
        ],
        "answerId": "A",
        "explanation": "동백 冬柏은 겨울 동, 측백 백 자를 써서 겨울에 피는 꽃이라는 뜻을 담고 있어요.",
        "scoring": {
          "correctDeltaSec": 10,
          "wrongDeltaSec": 0
        }
      },
      {
        "id": "dq-s2-361-2",
        "type": "MULTI_CHOICE",
        "questionKind": "READING_COMPREHENSION",
        "competency": "문장 독해력",
        "passage": "동백꽃은 꽃잎이 한 장씩 떨어지지 않고, 꽃송이째 툭 하고 떨어집니다. 그 모습이 처연하면서도 아름답습니다.",
        "stem": "동백꽃이 지는 모습은?",
        "choices": [
          {
            "id": "A",
            "text": "꽃송이째 떨어짐"
          },
          {
            "id": "B",
            "text": "꽃잎이 하나씩 날린다"
          },
          {
            "id": "C",
            "text": "민들레 씨앗처럼 날아간다"
          },
          {
            "id": "D",
            "text": "하늘로 솟구친다"
          }
        ],
        "answerId": "A",
        "explanation": "가장 아름답게 피었을 때 통째로 떨어지는 것이 동백꽃의 가장 큰 특징이자 매력이에요.",
        "scoring": {
          "correctDeltaSec": 10,
          "wrongDeltaSec": 0
        }
      },
      {
        "id": "dq-s2-361-3",
        "type": "MULTI_CHOICE",
        "questionKind": "STRUCTURE_READING",
        "competency": "구조 독해력",
        "passage": "동백나무의 쓰임. 1 관상용. 2 기름 동백기름. 3 가구 목재. 4 종이 만들기.",
        "stem": "동백나무로 주로 하지 않는 것은?",
        "choices": [
          {
            "id": "A",
            "text": "4"
          },
          {
            "id": "B",
            "text": "1"
          },
          {
            "id": "C",
            "text": "2"
          },
          {
            "id": "D",
            "text": "3"
          }
        ],
        "answerId": "A",
        "explanation": "꽃은 보고, 열매 기름은 머리에 바르거나 식용으로, 나무는 단단하여 가구 재료로 쓰지만 종이 원료로 쓰지는 않아요.",
        "scoring": {
          "correctDeltaSec": 10,
          "wrongDeltaSec": 0
        }
      },
      {
        "id": "dq-s2-361-4",
        "type": "MULTI_CHOICE",
        "questionKind": "BACKGROUND_KNOWLEDGE",
        "competency": "배경지식",
        "passage": "동백꽃은 향기가 없는 대신 꿀이 많아서 '이 새'가 꿀을 먹으며 꽃가루를 옮겨 줍니다.",
        "stem": "동백꽃을 도와주는 새는?",
        "choices": [
          {
            "id": "A",
            "text": "동박새"
          },
          {
            "id": "B",
            "text": "독수리"
          },
          {
            "id": "C",
            "text": "타조"
          },
          {
            "id": "D",
            "text": "펭귄"
          }
        ],
        "answerId": "A",
        "explanation": "겨울에는 곤충이 없어서 동박새나 직박구리 같은 새들이 꿀을 먹으러 오면서 수분을 도와주는 조매화예요.",
        "scoring": {
          "correctDeltaSec": 10,
          "wrongDeltaSec": 0
        }
      },
      {
        "id": "dq-s2-361-5",
        "type": "MULTI_CHOICE",
        "questionKind": "INFERENCE",
        "competency": "추론",
        "passage": "옛날 여인들은 머릿결을 곱게 하기 위해 동백나무 열매에서 짠 기름을 머리에 발랐습니다.",
        "stem": "동백기름의 효과는?",
        "choices": [
          {
            "id": "A",
            "text": "머릿결 윤기"
          },
          {
            "id": "B",
            "text": "머리카락을 빠지게 함"
          },
          {
            "id": "C",
            "text": "머리를 하얗게 염색함"
          },
          {
            "id": "D",
            "text": "머리 가려움을 유발함"
          }
        ],
        "answerId": "A",
        "explanation": "천연 오일인 동백기름은 푸석한 머리카락에 영양을 주고 윤기를 흐르게 하는 효과가 있어요.",
        "scoring": {
          "correctDeltaSec": 10,
          "wrongDeltaSec": 0
        }
      },
      {
        "id": "dq-s2-361-6",
        "type": "MULTI_CHOICE",
        "questionKind": "CRITICAL_THINKING",
        "competency": "비판적 사고",
        "passage": "A: \"동백꽃이 예쁘니까 꺾어서 집에 가져가야지.\"\nB: \"다음 사람들도 예쁜 꽃을 볼 수 있게 눈으로만 감상하자.\"",
        "stem": "누구의 행동이 자연을 보호하나요?",
        "choices": [
          {
            "id": "A",
            "text": "B"
          },
          {
            "id": "B",
            "text": "A"
          },
          {
            "id": "C",
            "text": "둘 다 나쁘다"
          },
          {
            "id": "D",
            "text": "꽃을 먹는다"
          }
        ],
        "answerId": "A",
        "explanation": "나 하나쯤이야 하고 꽃을 꺾으면 결국 아무도 꽃을 볼 수 없게 되므로, 있는 그대로 아껴 주어야 해요.",
        "scoring": {
          "correctDeltaSec": 10,
          "wrongDeltaSec": 0
        }
      },
      {
        "id": "dq-s2-361-7",
        "type": "MULTI_CHOICE",
        "questionKind": "CREATIVE_THINKING",
        "competency": "창의적 사고",
        "passage": "\"흰 눈 사이로 붉게 피어난 동백꽃은 겨울 숲이 바르는 __________________.\"",
        "stem": "동백꽃을 비유한 표현은?",
        "choices": [
          {
            "id": "A",
            "text": "빨간 립스틱"
          },
          {
            "id": "B",
            "text": "검은 선글라스 같아요"
          },
          {
            "id": "C",
            "text": "파란 마스크 같아요"
          },
          {
            "id": "D",
            "text": "노란 모자 같아요"
          }
        ],
        "answerId": "A",
        "explanation": "하얀 설원 속에 선명하게 붉은 동백꽃이 핀 모습이 마치 입술에 붉은 연지를 바른 것처럼 보여요.",
        "scoring": {
          "correctDeltaSec": 10,
          "wrongDeltaSec": 0
        }
      },
      {
        "id": "dq-s2-361-8",
        "type": "MULTI_CHOICE",
        "questionKind": "PROBLEM_SOLVING",
        "competency": "문제 해결",
        "passage": "집 마당에 동백나무를 심었는데 꽃이 피지 않아요.",
        "stem": "어떻게 해야 할까요?",
        "choices": [
          {
            "id": "A",
            "text": "햇빛과 물 확인"
          },
          {
            "id": "B",
            "text": "나무를 뽑아서 버린다"
          },
          {
            "id": "C",
            "text": "뜨거운 물을 붓는다"
          },
          {
            "id": "D",
            "text": "나뭇가지를 다 자른다"
          }
        ],
        "answerId": "A",
        "explanation": "식물이 꽃을 피우려면 적절한 햇빛, 온도, 수분, 양분 등이 필요하므로 환경을 점검해 봐야 해요.",
        "scoring": {
          "correctDeltaSec": 10,
          "wrongDeltaSec": 0
        }
      },
      {
        "id": "dq-s2-361-9",
        "type": "SENTENCE_BUILDING",
        "questionKind": "SENTENCE_BUILDING",
        "competency": "표현력",
        "stem": "글의 내용을 바탕으로 빈칸을 채워 요약 문장을 완성하세요.",
        "passage": "동백꽃은 추운 겨울에 붉은 꽃을 피웁니다. 꽃이 질 때는 송이째 툭 떨어지는 것이 특징입니다.",
        "correctSentence": "겨울에 붉게 피고 송이째 떨어집니다.",
        "sentenceParts": [
          {
            "answer": "겨울에",
            "distractors": [
              "여름에",
              "가을에",
              "봄에"
            ]
          },
          {
            "answer": "붉게",
            "distractors": [
              "파랗게",
              "검게",
              "투명하게"
            ]
          },
          {
            "answer": "피고",
            "distractors": [
              "죽고",
              "울고",
              "자고"
            ]
          },
          {
            "answer": "송이째",
            "distractors": [
              "잎만",
              "가지만",
              "뿌리째"
            ]
          },
          {
            "answer": "떨어집니다.",
            "distractors": [
              "올라갑니다.",
              "날아갑니다.",
              "도망갑니다."
            ]
          }
        ],
        "scoring": {
          "correctDeltaSec": 10,
          "wrongDeltaSec": 0
        }
      },
      {
        "id": "dq-s2-361-10",
        "type": "MULTI_CHOICE",
        "questionKind": "GRAMMAR",
        "competency": "문법 또는 어법",
        "stem": "다음 낱말 중 '동백나무의 열매'를 나타내는 말은?",
        "choices": [
          {
            "id": "A",
            "text": "동백"
          },
          {
            "id": "B",
            "text": "동베"
          },
          {
            "id": "C",
            "text": "동배"
          },
          {
            "id": "D",
            "text": "돈백"
          }
        ],
        "answerId": "A",
        "explanation": "동백나무의 열매를 줄여서 '동백'이라고도 불러요. '동백 기름'은 이 열매에서 짠 기름이에요.",
        "scoring": {
          "correctDeltaSec": 10,
          "wrongDeltaSec": 0
        }
      }
    ]
  }
}
